{"type":"FeatureCollection","features":[{"type":"Feature","bbox":[17.3775,-3.3202,17.3775,-3.3202],"geometry":{"type":"Point","coordinates":[17.3775,-3.3202]},"properties":{"eventtype":"FL","eventid":1102982,"episodeid":8,"eventname":"","glide":"","name":"Flood in Republic of Congo","description":"Flood in Republic of Congo","htmldescription":"Green Flood in Republic of Congo from: 24 Oct 2024 01 to: 05 Dec 2024 01.","icon":"https://www.gdacs.org/images/gdacs_icons/maps/Green/FL.png","iconoverall":"https://www.gdacs.org/images/gdacs_icons/maps/Green/FL.png","url":{"geometry":"https://www.gdacs.org/gdacsapi/api/polygons/getgeometry?eventtype=FL&eventid=1102982&episodeid=8","report":"https://www.gdacs.org/report.aspx?eventid=1102982&episodeid=8&eventtype=FL","details":"https://www.gdacs.org/gdacsapi/api/events/geteventdata?eventtype=FL&eventid=1102982"},"alertlevel":"Green","alertscore":1,"episodealertlevel":"Green","episodealertscore":0.5,"istemporary":"false","iscurrent":"false","country":"Republic of Congo","fromdate":"2024-10-24T01:00:00","todate":"2024-12-05T01:00:00","datemodified":"2024-12-06T10:56:57","iso3":"COG","source":"GLOFAS","sourceid":"","polygonlabel":"Centroid","Class":"Point_Centroid","affectedcountries":[{"iso2":"CG","iso3":"COG","countryname":"Republic of Congo"}],"severitydata":{"severity":0.0,"severitytext":"Magnitude 0 ","severityunit":""}}},{"type":"Feature","bbox":[119.8543,-3.087,119.8543,-3.087],"geometry":{"type":"Point","coordinates":[119.8543,-3.087]},"properties":{"eventtype":"FL","eventid":1102928,"episodeid":13,"eventname":"","glide":"","name":"Flood in Indonesia","description":"Flood in Indonesia","htmldescription":"Green Flood in Indonesia from: 18 Sep 2024 01 to: 15 Nov 2024 01.","icon":"https://www.gdacs.org/images/gdacs_icons/maps/Green/FL.png","iconoverall":"https://www.gdacs.org/images/gdacs_icons/maps/Green/FL.png","url":{"geometry":"https://www.gdacs.org/gdacsapi/api/polygons/getgeometry?eventtype=FL&eventid=1102928&episodeid=13","report":"https://www.gdacs.org/report.aspx?eventid=1102928&episodeid=13&eventtype=FL","details":"https://www.gdacs.org/gdacsapi/api/events/geteventdata?eventtype=FL&eventid=1102928"},"alertlevel":"Green","alertscore":1,"episodealertlevel":"Green","episodealertscore":0.5,"istemporary":"false","iscurrent":"false","country":"Indonesia","fromdate":"2024-09-18T01:00:00","todate":"2024-11-15T01:00:00","datemodified":"2024-11-19T07:17:06","iso3":"IDN","source":"GLOFAS","sourceid":"","polygonlabel":"Centroid","Class":"Point_Centroid","affectedcountries":[{"iso2":"ID","iso3":"IDN","countryname":"Indonesia"}],"severitydata":{"severity":0.0,"severitytext":"Magnitude 0 ","severityunit":""}}},{"type":"Feature","bbox":[0.4475,40.5968,0.4475,40.5968],"geometry":{"type":"Point","coordinates":[0.4475,40.5968]},"properties":{"eventtype":"FL","eventid":1102955,"episodeid":9,"eventname":"","glide":"FL-2024-000199-ESP","name":"Flood in Spain","description":"Flood in Spain","htmldescription":"Green Flood in Spain from: 11 Oct 2024 01 to: 15 Nov 2024 01.","icon":"https://www.gdacs.org/images/gdacs_icons/maps/Green/FL.png","iconoverall":"https://www.gdacs.org/images/gdacs_icons/maps/Green/FL.png","url":{"geometry":"https://www.gdacs.org/gdacsapi/api/polygons/getgeometry?eventtype=FL&eventid=1102955&episodeid=9","report":"https://www.gdacs.org/report.aspx?eventid=1102955&episodeid=9&eventtype=FL","details":"https://www.gdacs.org/gdacsapi/api/events/geteventdata?eventtype=FL&eventid=1102955"},"alertlevel":"Green","alertscore":1,"episodealertlevel":"Green","episodealertscore":0.5,"istemporary":"false","iscurrent":"false","country":"Spain","fromdate":"2024-10-11T01:00:00","todate":"2024-11-15T01:00:00","datemodified":"2024-11-15T09:28:15","iso3":"ESP","source":"GLOFAS","sourceid":"","polygonlabel":"Centroid","Class":"Point_Centroid","affectedcountries":[{"iso2":"ES","iso3":"ESP","countryname":"Spain"}],"severitydata":{"severity":0.0,"severitytext":"Magnitude 0 ","severityunit":""}}},{"type":"Feature","bbox":[-73.5208,6.9288,-73.5208,6.9288],"geometry":{"type":"Point","coordinates":[-73.5208,6.9288]},"properties":{"eventtype":"FL","eventid":1102988,"episodeid":5,"eventname":"","glide":"","name":"Flood in Colombia","description":"Flood in Colombia","htmldescription":"Green Flood in Colombia from: 31 Oct 2024 01 to: 11 Nov 2024 01.","icon":"https://www.gdacs.org/images/gdacs_icons/maps/Green/FL.png","iconoverall":"https://www.gdacs.org/images/gdacs_icons/maps/Green/FL.png","url":{"geometry":"https://www.gdacs.org/gdacsapi/api/polygons/getgeometry?eventtype=FL&eventid=1102988&episodeid=5","report":"https://www.gdacs.org/report.aspx?eventid=1102988&episodeid=5&eventtype=FL","details":"https://www.gdacs.org/gdacsapi/api/events/geteventdata?eventtype=FL&eventid=1102988"},"alertlevel":"Green","alertscore":1,"episodealertlevel":"Green","episodealertscore":0.5,"istemporary":"false","iscurrent":"false","country":"Colombia","fromdate":"2024-10-31T01:00:00","todate":"2024-11-11T01:00:00","datemodified":"2024-11-22T14:30:19","iso3":"COL","source":"GLOFAS","sourceid":"","polygonlabel":"Centroid","Class":"Point_Centroid","affectedcountries":[{"iso2":"CO","iso3":"COL","countryname":"Colombia"}],"severitydata":{"severity":0.0,"severitytext":"Magnitude 0 ","severityunit":""}}},{"type":"Feature","bbox":[106.1043,17.8997,106.1043,17.8997],"geometry":{"type":"Point","coordinates":[106.1043,17.8997]},"properties":{"eventtype":"FL","eventid":1102985,"episodeid":3,"eventname":"","glide":"","name":"Flood in Vietnam","description":"Flood in Vietnam","htmldescription":"Green Flood in Vietnam from: 27 Oct 2024 01 to: 07 Nov 2024 01.","icon":"https://www.gdacs.org/images/gdacs_icons/maps/Green/FL.png","iconoverall":"https://www.gdacs.org/images/gdacs_icons/maps/Green/FL.png","url":{"geometry":"https://www.gdacs.org/gdacsapi/api/polygons/getgeometry?eventtype=FL&eventid=1102985&episodeid=3","report":"https://www.gdacs.org/report.aspx?eventid=1102985&episodeid=3&eventtype=FL","details":"https://www.gdacs.org/gdacsapi/api/events/geteventdata?eventtype=FL&eventid=1102985"},"alertlevel":"Green","alertscore":1,"episodealertlevel":"Green","episodealertscore":0.5,"istemporary":"false","iscurrent":"false","country":"Vietnam","fromdate":"2024-10-27T01:00:00","todate":"2024-11-07T01:00:00","datemodified":"2024-11-07T06:45:11","iso3":"VNM","source":"GLOFAS","sourceid":"","polygonlabel":"Centroid","Class":"Point_Centroid","affectedcountries":[{"iso2":"VN","iso3":"VNM","countryname":"Vietnam"}],"severitydata":{"severity":0.0,"severitytext":"Magnitude 0 ","severityunit":""}}},{"type":"Feature","bbox":[-2.6232,39.4178,-2.6232,39.4178],"geometry":{"type":"Point","coordinates":[-2.6232,39.4178]},"properties":{"eventtype":"FL","eventid":1102983,"episodeid":2,"eventname":"","glide":"FL-2024-000199-ESP","name":"Flood in Spain","description":"Flood in Spain","htmldescription":"Orange Flood in Spain from: 27 Oct 2024 15 to: 04 Nov 2024 11.","icon":"https://www.gdacs.org/images/gdacs_icons/maps/Green/FL.png","iconoverall":"https://www.gdacs.org/images/gdacs_icons/maps/Orange/FL.png","url":{"geometry":"https://www.gdacs.org/gdacsapi/api/polygons/getgeometry?eventtype=FL&eventid=1102983&episodeid=2","report":"https://www.gdacs.org/report.aspx?eventid=1102983&episodeid=2&eventtype=FL","details":"https://www.gdacs.org/gdacsapi/api/events/geteventdata?eventtype=FL&eventid=1102983"},"alertlevel":"Orange","alertscore":2,"episodealertlevel":"Green","episodealertscore":0.5,"istemporary":"false","iscurrent":"false","country":"Spain","fromdate":"2024-10-27T15:00:00","todate":"2024-11-04T11:00:00","datemodified":"2025-01-05T12:10:23","iso3":"ESP","source":"GLOFAS","sourceid":"","polygonlabel":"Centroid","Class":"Point_Centroid","affectedcountries":[{"iso2":"ES","iso3":"ESP","countryname":"Spain"}],"severitydata":{"severity":0.0,"severitytext":"Magnitude 0 ","severityunit":""}}},{"type":"Feature","bbox":[4.7877,35.6722,4.7877,35.6722],"geometry":{"type":"Point","coordinates":[4.7877,35.6722]},"properties":{"eventtype":"FL","eventid":1102981,"episodeid":2,"eventname":"","glide":"","name":"Flood in Algeria","description":"Flood in Algeria","htmldescription":"Green Flood in Algeria from: 24 Oct 2024 01 to: 03 Nov 2024 01.","icon":"https://www.gdacs.org/images/gdacs_icons/maps/Green/FL.png","iconoverall":"https://www.gdacs.org/images/gdacs_icons/maps/Green/FL.png","url":{"geometry":"https://www.gdacs.org/gdacsapi/api/polygons/getgeometry?eventtype=FL&eventid=1102981&episodeid=2","report":"https://www.gdacs.org/report.aspx?eventid=1102981&episodeid=2&eventtype=FL","details":"https://www.gdacs.org/gdacsapi/api/events/geteventdata?eventtype=FL&eventid=1102981"},"alertlevel":"Green","alertscore":1,"episodealertlevel":"Green","episodealertscore":0.5,"istemporary":"false","iscurrent":"false","country":"Algeria","fromdate":"2024-10-24T01:00:00","todate":"2024-11-03T01:00:00","datemodified":"2024-11-05T10:05:13","iso3":"DZA","source":"GLOFAS","sourceid":"","polygonlabel":"Centroid","Class":"Point_Centroid","affectedcountries":[{"iso2":"DZ","iso3":"DZA","countryname":"Algeria"}],"severitydata":{"severity":0.0,"severitytext":"Magnitude 0 ","severityunit":""}}},{"type":"Feature","bbox":[6.6591,60.3258,6.6591,60.3258],"geometry":{"type":"Point","coordinates":[6.6591,60.3258]},"properties":{"eventtype":"FL","eventid":1102984,"episodeid":1,"eventname":"","glide":"","name":"Flood in Norway","description":"Flood in Norway","htmldescription":"Green Flood in Norway from: 31 Oct 2024 01 to: 02 Nov 2024 01.","icon":"https://www.gdacs.org/images/gdacs_icons/maps/Green/FL.png","iconoverall":"https://www.gdacs.org/images/gdacs_icons/maps/Green/FL.png","url":{"geometry":"https://www.gdacs.org/gdacsapi/api/polygons/getgeometry?eventtype=FL&eventid=1102984&episodeid=1","report":"https://www.gdacs.org/report.aspx?eventid=1102984&episodeid=1&eventtype=FL","details":"https://www.gdacs.org/gdacsapi/api/events/geteventdata?eventtype=FL&eventid=1102984"},"alertlevel":"Green","alertscore":1,"episodealertlevel":"Green","episodealertscore":0.5,"istemporary":"false","iscurrent":"false","country":"Norway","fromdate":"2024-10-31T01:00:00","todate":"2024-11-02T01:00:00","datemodified":"2024-11-05T06:14:25","iso3":"NOR","source":"GLOFAS","sourceid":"","polygonlabel":"Centroid","Class":"Point_Centroid","affectedcountries":[{"iso2":"NO","iso3":"NOR","countryname":"Norway"}],"severitydata":{"severity":0.0,"severitytext":"Magnitude 0 ","severityunit":""}}},{"type":"Feature","bbox":[8.8568,39.1949,8.8568,39.1949],"geometry":{"type":"Point","coordinates":[8.8568,39.1949]},"properties":{"eventtype":"FL","eventid":1102961,"episodeid":10,"eventname":"","glide":"","name":"Flood in Italy","description":"Flood in Italy","htmldescription":"Green Flood in Italy from: 16 Oct 2024 01 to: 28 Oct 2024 01.","icon":"https://www.gdacs.org/images/gdacs_icons/maps/Green/FL.png","iconoverall":"https://www.gdacs.org/images/gdacs_icons/maps/Green/FL.png","url":{"geometry":"https://www.gdacs.org/gdacsapi/api/polygons/getgeometry?eventtype=FL&eventid=1102961&episodeid=10","report":"https://www.gdacs.org/report.aspx?eventid=1102961&episodeid=10&eventtype=FL","details":"https://www.gdacs.org/gdacsapi/api/events/geteventdata?eventtype=FL&eventid=1102961"},"alertlevel":"Green","alertscore":1,"episodealertlevel":"Green","episodealertscore":0.5,"istemporary":"false","iscurrent":"false","country":"Italy","fromdate":"2024-10-16T01:00:00","todate":"2024-10-28T01:00:00","datemodified":"2024-10-30T07:32:39","iso3":"ITA","source":"GLOFAS","sourceid":"","polygonlabel":"Centroid","Class":"Point_Centroid","affectedcountries":[{"iso2":"IT","iso3":"ITA","countryname":"Italy"}],"severitydata":{"severity":0.0,"severitytext":"Magnitude 0 ","severityunit":""}}},{"type":"Feature","bbox":[6.4314,43.4273,6.4314,43.4273],"geometry":{"type":"Point","coordinates":[6.4314,43.4273]},"properties":{"eventtype":"FL","eventid":1102931,"episodeid":6,"eventname":"","glide":"","name":"Flood in France","description":"Flood in France","htmldescription":"Green Flood in France from: 01 Oct 2024 01 to: 26 Oct 2024 01.","icon":"https://www.gdacs.org/images/gdacs_icons/maps/Green/FL.png","iconoverall":"https://www.gdacs.org/images/gdacs_icons/maps/Green/FL.png","url":{"geometry":"https://www.gdacs.org/gdacsapi/api/polygons/getgeometry?eventtype=FL&eventid=1102931&episodeid=6","report":"https://www.gdacs.org/report.aspx?eventid=1102931&episodeid=6&eventtype=FL","details":"https://www.gdacs.org/gdacsapi/api/events/geteventdata?eventtype=FL&eventid=1102931"},"alertlevel":"Green","alertscore":1,"episodealertlevel":"Green","episodealertscore":0.5,"istemporary":"false","iscurrent":"false","country":"France","fromdate":"2024-10-01T01:00:00","todate":"2024-10-26T01:00:00","datemodified":"2024-10-26T12:03:13","iso3":"FRA","source":"GLOFAS","sourceid":"","polygonlabel":"Centroid","Class":"Point_Centroid","affectedcountries":[{"iso2":"FR","iso3":"FRA","countryname":"France"}],"severitydata":{"severity":0.0,"severitytext":"Magnitude 0 ","severityunit":""}}},{"type":"Feature","bbox":[84.6897,20.5431,84.6897,20.5431],"geometry":{"type":"Point","coordinates":[84.6897,20.5431]},"properties":{"eventtype":"FL","eventid":1102974,"episodeid":2,"eventname":"","glide":"FL-2024-000197-IND","name":"Flood in India","description":"Flood in India","htmldescription":"Red Flood in India from: 20 Oct 2024 01 to: 26 Oct 2024 01.","icon":"https://www.gdacs.org/images/gdacs_icons/maps/Red/FL.png","iconoverall":"https://www.gdacs.org/images/gdacs_icons/maps/Red/FL.png","url":{"geometry":"https://www.gdacs.org/gdacsapi/api/polygons/getgeometry?eventtype=FL&eventid=1102974&episodeid=2","report":"https://www.gdacs.org/report.aspx?eventid=1102974&episodeid=2&eventtype=FL","details":"https://www.gdacs.org/gdacsapi/api/events/geteventdata?eventtype=FL&eventid=1102974"},"alertlevel":"Red","alertscore":3,"episodealertlevel":"Red","episodealertscore":2.5,"istemporary":"false","iscurrent":"false","country":"India","fromdate":"2024-10-20T01:00:00","todate":"2024-10-26T01:00:00","datemodified":"2024-10-28T08:01:26","iso3":"IND","source":"GLOFAS","sourceid":"","polygonlabel":"Centroid","Class":"Point_Centroid","affectedcountries":[{"iso2":"IN","iso3":"IND","countryname":"India"}],"severitydata":{"severity":0.0,"severitytext":"Magnitude 0 ","severityunit":""}}},{"type":"Feature","bbox":[-57.5081,-25.2451,-57.5081,-25.2451],"geometry":{"type":"Point","coordinates":[-57.5081,-25.2451]},"properties":{"eventtype":"FL","eventid":1102979,"episodeid":1,"eventname":"","glide":"","name":"Flood in Uruguay","description":"Flood in Uruguay","htmldescription":"Green Flood in Uruguay from: 23 Oct 2024 01 to: 25 Oct 2024 01.","icon":"https://www.gdacs.org/images/gdacs_icons/maps/Green/FL.png","iconoverall":"https://www.gdacs.org/images/gdacs_icons/maps/Green/FL.png","url":{"geometry":"https://www.gdacs.org/gdacsapi/api/polygons/getgeometry?eventtype=FL&eventid=1102979&episodeid=1","report":"https://www.gdacs.org/report.aspx?eventid=1102979&episodeid=1&eventtype=FL","details":"https://www.gdacs.org/gdacsapi/api/events/geteventdata?eventtype=FL&eventid=1102979"},"alertlevel":"Green","alertscore":1,"episodealertlevel":"Green","episodealertscore":0.5,"istemporary":"false","iscurrent":"false","country":"Uruguay","fromdate":"2024-10-23T01:00:00","todate":"2024-10-25T01:00:00","datemodified":"2024-10-26T12:00:18","iso3":"URY","source":"GLOFAS","sourceid":"","polygonlabel":"Centroid","Class":"Point_Centroid","affectedcountries":[{"iso2":"UY","iso3":"URY","countryname":"Uruguay"}],"severitydata":{"severity":0.0,"severitytext":"Magnitude 0 ","severityunit":""}}},{"type":"Feature","bbox":[-75.1159,-11.964,-75.1159,-11.964],"geometry":{"type":"Point","coordinates":[-75.1159,-11.964]},"properties":{"eventtype":"FL","eventid":1102978,"episodeid":1,"eventname":"","glide":"","name":"Flood in Peru","description":"Flood in Peru","htmldescription":"Green Flood in Peru from: 22 Oct 2024 01 to: 24 Oct 2024 01.","icon":"https://www.gdacs.org/images/gdacs_icons/maps/Green/FL.png","iconoverall":"https://www.gdacs.org/images/gdacs_icons/maps/Green/FL.png","url":{"geometry":"https://www.gdacs.org/gdacsapi/api/polygons/getgeometry?eventtype=FL&eventid=1102978&episodeid=1","report":"https://www.gdacs.org/report.aspx?eventid=1102978&episodeid=1&eventtype=FL","details":"https://www.gdacs.org/gdacsapi/api/events/geteventdata?eventtype=FL&eventid=1102978"},"alertlevel":"Green","alertscore":1,"episodealertlevel":"Green","episodealertscore":0.5,"istemporary":"false","iscurrent":"false","country":"Peru","fromdate":"2024-10-22T01:00:00","todate":"2024-10-24T01:00:00","datemodified":"2024-10-26T11:58:51","iso3":"PER","source":"GLOFAS","sourceid":"","polygonlabel":"Centroid","Class":"Point_Centroid","affectedcountries":[{"iso2":"PE","iso3":"PER","countryname":"Peru"}],"severitydata":{"severity":0.0,"severitytext":"Magnitude 0 ","severityunit":""}}},{"type":"Feature","bbox":[131.6649,32.5823,131.6649,32.5823],"geometry":{"type":"Point","coordinates":[131.6649,32.5823]},"properties":{"eventtype":"FL","eventid":1102976,"episodeid":1,"eventname":"","glide":"","name":"Flood in Japan","description":"Flood in Japan","htmldescription":"Green Flood in Japan from: 22 Oct 2024 01 to: 24 Oct 2024 01.","icon":"https://www.gdacs.org/images/gdacs_icons/maps/Green/FL.png","iconoverall":"https://www.gdacs.org/images/gdacs_icons/maps/Green/FL.png","url":{"geometry":"https://www.gdacs.org/gdacsapi/api/polygons/getgeometry?eventtype=FL&eventid=1102976&episodeid=1","report":"https://www.gdacs.org/report.aspx?eventid=1102976&episodeid=1&eventtype=FL","details":"https://www.gdacs.org/gdacsapi/api/events/geteventdata?eventtype=FL&eventid=1102976"},"alertlevel":"Green","alertscore":1,"episodealertlevel":"Green","episodealertscore":0.5,"istemporary":"false","iscurrent":"false","country":"Japan","fromdate":"2024-10-22T01:00:00","todate":"2024-10-24T01:00:00","datemodified":"2024-10-24T06:12:33","iso3":"JPN","source":"GLOFAS","sourceid":"","polygonlabel":"Centroid","Class":"Point_Centroid","affectedcountries":[{"iso2":"JP","iso3":"JPN","countryname":"Japan"}],"severitydata":{"severity":0.0,"severitytext":"Magnitude 0 ","severityunit":""}}},{"type":"Feature","bbox":[-162.5978,66.8982,-162.5978,66.8982],"geometry":{"type":"Point","coordinates":[-162.5978,66.8982]},"properties":{"eventtype":"FL","eventid":1102969,"episodeid":2,"eventname":"","glide":"","name":"Flood in United States","description":"Flood in United States","htmldescription":"Green Flood in United States from: 19 Oct 2024 01 to: 24 Oct 2024 01.","icon":"https://www.gdacs.org/images/gdacs_icons/maps/Green/FL.png","iconoverall":"https://www.gdacs.org/images/gdacs_icons/maps/Green/FL.png","url":{"geometry":"https://www.gdacs.org/gdacsapi/api/polygons/getgeometry?eventtype=FL&eventid=1102969&episodeid=2","report":"https://www.gdacs.org/report.aspx?eventid=1102969&episodeid=2&eventtype=FL","details":"https://www.gdacs.org/gdacsapi/api/events/geteventdata?eventtype=FL&eventid=1102969"},"alertlevel":"Green","alertscore":1,"episodealertlevel":"Green","episodealertscore":0.5,"istemporary":"false","iscurrent":"false","country":"United States","fromdate":"2024-10-19T01:00:00","todate":"2024-10-24T01:00:00","datemodified":"2024-10-26T11:56:59","iso3":"USA","source":"GLOFAS","sourceid":"","polygonlabel":"Centroid","Class":"Point_Centroid","affectedcountries":[{"iso2":"US","iso3":"USA","countryname":"United States"}],"severitydata":{"severity":0.0,"severitytext":"Magnitude 0 ","severityunit":""}}},{"type":"Feature","bbox":[49.8328,40.3756,49.8328,40.3756],"geometry":{"type":"Point","coordinates":[49.8328,40.3756]},"properties":{"eventtype":"FL","eventid":1102965,"episodeid":2,"eventname":"","glide":"","name":"Flood in Azerbaijan","description":"Flood in Azerbaijan","htmldescription":"Green Flood in Azerbaijan from: 12 Oct 2024 01 to: 23 Oct 2024 01.","icon":"https://www.gdacs.org/images/gdacs_icons/maps/Green/FL.png","iconoverall":"https://www.gdacs.org/images/gdacs_icons/maps/Green/FL.png","url":{"geometry":"https://www.gdacs.org/gdacsapi/api/polygons/getgeometry?eventtype=FL&eventid=1102965&episodeid=2","report":"https://www.gdacs.org/report.aspx?eventid=1102965&episodeid=2&eventtype=FL","details":"https://www.gdacs.org/gdacsapi/api/events/geteventdata?eventtype=FL&eventid=1102965"},"alertlevel":"Green","alertscore":1,"episodealertlevel":"Green","episodealertscore":0.5,"istemporary":"false","iscurrent":"false","country":"Azerbaijan","fromdate":"2024-10-12T01:00:00","todate":"2024-10-23T01:00:00","datemodified":"2024-10-26T11:53:58","iso3":"AZE","source":"GLOFAS","sourceid":"","polygonlabel":"Centroid","Class":"Point_Centroid","affectedcountries":[{"iso2":"AZ","iso3":"AZE","countryname":"Azerbaijan"}],"severitydata":{"severity":0.0,"severitytext":"Magnitude 0 ","severityunit":""}}},{"type":"Feature","bbox":[13.5895,-1.6344,13.5895,-1.6344],"geometry":{"type":"Point","coordinates":[13.5895,-1.6344]},"properties":{"eventtype":"FL","eventid":1102975,"episodeid":1,"eventname":"","glide":"","name":"Flood in Gabon","description":"Flood in Gabon","htmldescription":"Green Flood in Gabon from: 21 Oct 2024 01 to: 23 Oct 2024 01.","icon":"https://www.gdacs.org/images/gdacs_icons/maps/Green/FL.png","iconoverall":"https://www.gdacs.org/images/gdacs_icons/maps/Green/FL.png","url":{"geometry":"https://www.gdacs.org/gdacsapi/api/polygons/getgeometry?eventtype=FL&eventid=1102975&episodeid=1","report":"https://www.gdacs.org/report.aspx?eventid=1102975&episodeid=1&eventtype=FL","details":"https://www.gdacs.org/gdacsapi/api/events/geteventdata?eventtype=FL&eventid=1102975"},"alertlevel":"Green","alertscore":1,"episodealertlevel":"Green","episodealertscore":0.5,"istemporary":"false","iscurrent":"false","country":"Gabon","fromdate":"2024-10-21T01:00:00","todate":"2024-10-23T01:00:00","datemodified":"2024-10-24T05:52:28","iso3":"GAB","source":"GLOFAS","sourceid":"","polygonlabel":"Centroid","Class":"Point_Centroid","affectedcountries":[{"iso2":"GA","iso3":"GAB","countryname":"Gabon"}],"severitydata":{"severity":0.0,"severitytext":"Magnitude 0 ","severityunit":""}}},{"type":"Feature","bbox":[-75.2035,20.1432,-75.2035,20.1432],"geometry":{"type":"Point","coordinates":[-75.2035,20.1432]},"properties":{"eventtype":"FL","eventid":1102973,"episodeid":1,"eventname":"","glide":"","name":"Flood in Cuba","description":"Flood in Cuba","htmldescription":"Green Flood in Cuba from: 21 Oct 2024 01 to: 23 Oct 2024 01.","icon":"https://www.gdacs.org/images/gdacs_icons/maps/Green/FL.png","iconoverall":"https://www.gdacs.org/images/gdacs_icons/maps/Green/FL.png","url":{"geometry":"https://www.gdacs.org/gdacsapi/api/polygons/getgeometry?eventtype=FL&eventid=1102973&episodeid=1","report":"https://www.gdacs.org/report.aspx?eventid=1102973&episodeid=1&eventtype=FL","details":"https://www.gdacs.org/gdacsapi/api/events/geteventdata?eventtype=FL&eventid=1102973"},"alertlevel":"Green","alertscore":1,"episodealertlevel":"Green","episodealertscore":0.5,"istemporary":"false","iscurrent":"false","country":"Cuba","fromdate":"2024-10-21T01:00:00","todate":"2024-10-23T01:00:00","datemodified":"2024-10-23T05:32:23","iso3":"CUB","source":"GLOFAS","sourceid":"","polygonlabel":"Centroid","Class":"Point_Centroid","affectedcountries":[{"iso2":"CU","iso3":"CUB","countryname":"Cuba"}],"severitydata":{"severity":0.0,"severitytext":"Magnitude 0 ","severityunit":""}}},{"type":"Feature","bbox":[58.1065,33.1296,58.1065,33.1296],"geometry":{"type":"Point","coordinates":[58.1065,33.1296]},"properties":{"eventtype":"FL","eventid":1102980,"episodeid":1,"eventname":"","glide":"","name":"Flood in Islamic Republic of Iran","description":"Flood in Islamic Republic of Iran","htmldescription":"Green Flood in Islamic Republic of Iran from: 21 Oct 2024 01 to: 23 Oct 2024 01.","icon":"https://www.gdacs.org/images/gdacs_icons/maps/Green/FL.png","iconoverall":"https://www.gdacs.org/images/gdacs_icons/maps/Green/FL.png","url":{"geometry":"https://www.gdacs.org/gdacsapi/api/polygons/getgeometry?eventtype=FL&eventid=1102980&episodeid=1","report":"https://www.gdacs.org/report.aspx?eventid=1102980&episodeid=1&eventtype=FL","details":"https://www.gdacs.org/gdacsapi/api/events/geteventdata?eventtype=FL&eventid=1102980"},"alertlevel":"Green","alertscore":1,"episodealertlevel":"Green","episodealertscore":0.5,"istemporary":"false","iscurrent":"false","country":"Islamic Republic of Iran","fromdate":"2024-10-21T01:00:00","todate":"2024-10-23T01:00:00","datemodified":"2024-10-28T07:04:55","iso3":"IRN","source":"GLOFAS","sourceid":"","polygonlabel":"Centroid","Class":"Point_Centroid","affectedcountries":[{"iso2":"IR","iso3":"IRN","countryname":"Islamic Republic of Iran"}],"severitydata":{"severity":0.0,"severitytext":"Magnitude 0 ","severityunit":""}}},{"type":"Feature","bbox":[25.3978,-33.7679,25.3978,-33.7679],"geometry":{"type":"Point","coordinates":[25.3978,-33.7679]},"properties":{"eventtype":"FL","eventid":1102959,"episodeid":2,"eventname":"","glide":"","name":"Flood in South Africa","description":"Flood in South Africa","htmldescription":"Green Flood in South Africa from: 15 Oct 2024 01 to: 23 Oct 2024 01.","icon":"https://www.gdacs.org/images/gdacs_icons/maps/Green/FL.png","iconoverall":"https://www.gdacs.org/images/gdacs_icons/maps/Green/FL.png","url":{"geometry":"https://www.gdacs.org/gdacsapi/api/polygons/getgeometry?eventtype=FL&eventid=1102959&episodeid=2","report":"https://www.gdacs.org/report.aspx?eventid=1102959&episodeid=2&eventtype=FL","details":"https://www.gdacs.org/gdacsapi/api/events/geteventdata?eventtype=FL&eventid=1102959"},"alertlevel":"Green","alertscore":1,"episodealertlevel":"Green","episodealertscore":0.5,"istemporary":"false","iscurrent":"false","country":"South Africa","fromdate":"2024-10-15T01:00:00","todate":"2024-10-23T01:00:00","datemodified":"2024-10-22T11:03:59","iso3":"ZAF","source":"GLOFAS","sourceid":"","polygonlabel":"Centroid","Class":"Point_Centroid","affectedcountries":[{"iso2":"ZA","iso3":"ZAF","countryname":"South Africa"}],"severitydata":{"severity":0.0,"severitytext":"Magnitude 0 ","severityunit":""}}},{"type":"Feature","bbox":[122.7312,12.7503,122.7312,12.7503],"geometry":{"type":"Point","coordinates":[122.7312,12.7503]},"properties":{"eventtype":"FL","eventid":1102952,"episodeid":4,"eventname":"","glide":"","name":"Flood in Philippines","description":"Flood in Philippines","htmldescription":"Green Flood in Philippines from: 12 Oct 2024 01 to: 23 Oct 2024 01.","icon":"https://www.gdacs.org/images/gdacs_icons/maps/Green/FL.png","iconoverall":"https://www.gdacs.org/images/gdacs_icons/maps/Green/FL.png","url":{"geometry":"https://www.gdacs.org/gdacsapi/api/polygons/getgeometry?eventtype=FL&eventid=1102952&episodeid=4","report":"https://www.gdacs.org/report.aspx?eventid=1102952&episodeid=4&eventtype=FL","details":"https://www.gdacs.org/gdacsapi/api/events/geteventdata?eventtype=FL&eventid=1102952"},"alertlevel":"Green","alertscore":1,"episodealertlevel":"Green","episodealertscore":0.5,"istemporary":"false","iscurrent":"false","country":"Philippines","fromdate":"2024-10-12T01:00:00","todate":"2024-10-23T01:00:00","datemodified":"2024-10-24T06:14:08","iso3":"PHL","source":"GLOFAS","sourceid":"","polygonlabel":"Centroid","Class":"Point_Centroid","affectedcountries":[{"iso2":"PH","iso3":"PHL","countryname":"Philippines"}],"severitydata":{"severity":0.0,"severitytext":"Magnitude 0 ","severityunit":""}}},{"type":"Feature","bbox":[-93.8527,16.5152,-93.8527,16.5152],"geometry":{"type":"Point","coordinates":[-93.8527,16.5152]},"properties":{"eventtype":"FL","eventid":1102964,"episodeid":2,"eventname":"","glide":"","name":"Flood in Mexico","description":"Flood in Mexico","htmldescription":"Green Flood in Mexico from: 16 Oct 2024 01 to: 22 Oct 2024 01.","icon":"https://www.gdacs.org/images/gdacs_icons/maps/Green/FL.png","iconoverall":"https://www.gdacs.org/images/gdacs_icons/maps/Green/FL.png","url":{"geometry":"https://www.gdacs.org/gdacsapi/api/polygons/getgeometry?eventtype=FL&eventid=1102964&episodeid=2","report":"https://www.gdacs.org/report.aspx?eventid=1102964&episodeid=2&eventtype=FL","details":"https://www.gdacs.org/gdacsapi/api/events/geteventdata?eventtype=FL&eventid=1102964"},"alertlevel":"Green","alertscore":1,"episodealertlevel":"Green","episodealertscore":0.5,"istemporary":"false","iscurrent":"false","country":"Mexico","fromdate":"2024-10-16T01:00:00","todate":"2024-10-22T01:00:00","datemodified":"2024-10-23T05:33:57","iso3":"MEX","source":"GLOFAS","sourceid":"","polygonlabel":"Centroid","Class":"Point_Centroid","affectedcountries":[{"iso2":"MX","iso3":"MEX","countryname":"Mexico"}],"severitydata":{"severity":0.0,"severitytext":"Magnitude 0 ","severityunit":""}}},{"type":"Feature","bbox":[41.23,43.15,41.23,43.15],"geometry":{"type":"Point","coordinates":[41.23,43.15]},"properties":{"eventtype":"FL","eventid":1102971,"episodeid":1,"eventname":"","glide":"","name":"Flood in Georgia","description":"Flood in Georgia","htmldescription":"Green Flood in Georgia from: 20 Oct 2024 01 to: 22 Oct 2024 01.","icon":"https://www.gdacs.org/images/gdacs_icons/maps/Green/FL.png","iconoverall":"https://www.gdacs.org/images/gdacs_icons/maps/Green/FL.png","url":{"geometry":"https://www.gdacs.org/gdacsapi/api/polygons/getgeometry?eventtype=FL&eventid=1102971&episodeid=1","report":"https://www.gdacs.org/report.aspx?eventid=1102971&episodeid=1&eventtype=FL","details":"https://www.gdacs.org/gdacsapi/api/events/geteventdata?eventtype=FL&eventid=1102971"},"alertlevel":"Green","alertscore":1,"episodealertlevel":"Green","episodealertscore":0.5,"istemporary":"false","iscurrent":"false","country":"Georgia","fromdate":"2024-10-20T01:00:00","todate":"2024-10-22T01:00:00","datemodified":"2024-10-23T04:42:23","iso3":"GEO","source":"GLOFAS","sourceid":"","polygonlabel":"Centroid","Class":"Point_Centroid","affectedcountries":[{"iso2":"GE","iso3":"GEO","countryname":"Georgia"}],"severitydata":{"severity":0.0,"severitytext":"Magnitude 0 ","severityunit":""}}},{"type":"Feature","bbox":[-123.1595,49.3311,-123.1595,49.3311],"geometry":{"type":"Point","coordinates":[-123.1595,49.3311]},"properties":{"eventtype":"FL","eventid":1102967,"episodeid":1,"eventname":"","glide":"","name":"Flood in Canada","description":"Flood in Canada","htmldescription":"Green Flood in Canada from: 19 Oct 2024 01 to: 21 Oct 2024 01.","icon":"https://www.gdacs.org/images/gdacs_icons/maps/Green/FL.png","iconoverall":"https://www.gdacs.org/images/gdacs_icons/maps/Green/FL.png","url":{"geometry":"https://www.gdacs.org/gdacsapi/api/polygons/getgeometry?eventtype=FL&eventid=1102967&episodeid=1","report":"https://www.gdacs.org/report.aspx?eventid=1102967&episodeid=1&eventtype=FL","details":"https://www.gdacs.org/gdacsapi/api/events/geteventdata?eventtype=FL&eventid=1102967"},"alertlevel":"Green","alertscore":1,"episodealertlevel":"Green","episodealertscore":0.5,"istemporary":"false","iscurrent":"false","country":"Canada","fromdate":"2024-10-19T01:00:00","todate":"2024-10-21T01:00:00","datemodified":"2024-10-21T05:22:28","iso3":"CAN","source":"GLOFAS","sourceid":"","polygonlabel":"Centroid","Class":"Point_Centroid","affectedcountries":[{"iso2":"CA","iso3":"CAN","countryname":"Canada"}],"severitydata":{"severity":0.0,"severitytext":"Magnitude 0 ","severityunit":""}}},{"type":"Feature","bbox":[15.3168,-4.3542,15.3168,-4.3542],"geometry":{"type":"Point","coordinates":[15.3168,-4.3542]},"properties":{"eventtype":"FL","eventid":1102968,"episodeid":1,"eventname":"","glide":"","name":"Flood in Democratic Republic of Congo","description":"Flood in Democratic Republic of Congo","htmldescription":"Green Flood in Democratic Republic of Congo from: 19 Oct 2024 01 to: 21 Oct 2024 01.","icon":"https://www.gdacs.org/images/gdacs_icons/maps/Green/FL.png","iconoverall":"https://www.gdacs.org/images/gdacs_icons/maps/Green/FL.png","url":{"geometry":"https://www.gdacs.org/gdacsapi/api/polygons/getgeometry?eventtype=FL&eventid=1102968&episodeid=1","report":"https://www.gdacs.org/report.aspx?eventid=1102968&episodeid=1&eventtype=FL","details":"https://www.gdacs.org/gdacsapi/api/events/geteventdata?eventtype=FL&eventid=1102968"},"alertlevel":"Green","alertscore":1,"episodealertlevel":"Green","episodealertscore":0.5,"istemporary":"false","iscurrent":"false","country":"Democratic Republic of Congo","fromdate":"2024-10-19T01:00:00","todate":"2024-10-21T01:00:00","datemodified":"2024-10-21T05:34:08","iso3":"COD","source":"GLOFAS","sourceid":"","polygonlabel":"Centroid","Class":"Point_Centroid","affectedcountries":[{"iso2":"CD","iso3":"COD","countryname":"Democratic Republic of Congo"}],"severitydata":{"severity":0.0,"severitytext":"Magnitude 0 ","severityunit":""}}},{"type":"Feature","bbox":[99.5211,15.0825,99.5211,15.0825],"geometry":{"type":"Point","coordinates":[99.5211,15.0825]},"properties":{"eventtype":"FL","eventid":1102925,"episodeid":3,"eventname":"","glide":"","name":"Flood in Thailand","description":"Flood in Thailand","htmldescription":"Green Flood in Thailand from: 01 Oct 2024 01 to: 21 Oct 2024 01.","icon":"https://www.gdacs.org/images/gdacs_icons/maps/Green/FL.png","iconoverall":"https://www.gdacs.org/images/gdacs_icons/maps/Green/FL.png","url":{"geometry":"https://www.gdacs.org/gdacsapi/api/polygons/getgeometry?eventtype=FL&eventid=1102925&episodeid=3","report":"https://www.gdacs.org/report.aspx?eventid=1102925&episodeid=3&eventtype=FL","details":"https://www.gdacs.org/gdacsapi/api/events/geteventdata?eventtype=FL&eventid=1102925"},"alertlevel":"Green","alertscore":1,"episodealertlevel":"Green","episodealertscore":0.5,"istemporary":"false","iscurrent":"false","country":"Thailand","fromdate":"2024-10-01T01:00:00","todate":"2024-10-21T01:00:00","datemodified":"2024-10-22T07:44:05","iso3":"THA","source":"GLOFAS","sourceid":"","polygonlabel":"Centroid","Class":"Point_Centroid","affectedcountries":[{"iso2":"TH","iso3":"THA","countryname":"Thailand"}],"severitydata":{"severity":0.0,"severitytext":"Magnitude 0 ","severityunit":""}}},{"type":"Feature","bbox":[18.7153,4.1761,18.7153,4.1761],"geometry":{"type":"Point","coordinates":[18.7153,4.1761]},"properties":{"eventtype":"FL","eventid":1102963,"episodeid":2,"eventname":"","glide":"","name":"Flood in Republic of Congo","description":"Flood in Republic of Congo","htmldescription":"Green Flood in Republic of Congo from: 09 Oct 2024 01 to: 20 Oct 2024 01.","icon":"https://www.gdacs.org/images/gdacs_icons/maps/Green/FL.png","iconoverall":"https://www.gdacs.org/images/gdacs_icons/maps/Green/FL.png","url":{"geometry":"https://www.gdacs.org/gdacsapi/api/polygons/getgeometry?eventtype=FL&eventid=1102963&episodeid=2","report":"https://www.gdacs.org/report.aspx?eventid=1102963&episodeid=2&eventtype=FL","details":"https://www.gdacs.org/gdacsapi/api/events/geteventdata?eventtype=FL&eventid=1102963"},"alertlevel":"Green","alertscore":1,"episodealertlevel":"Green","episodealertscore":0.5,"istemporary":"false","iscurrent":"false","country":"Republic of Congo","fromdate":"2024-10-09T01:00:00","todate":"2024-10-20T01:00:00","datemodified":"2024-11-05T10:06:38","iso3":"COG","source":"GLOFAS","sourceid":"","polygonlabel":"Centroid","Class":"Point_Centroid","affectedcountries":[{"iso2":"CG","iso3":"COG","countryname":"Republic of Congo"}],"severitydata":{"severity":0.0,"severitytext":"Magnitude 0 ","severityunit":""}}},{"type":"Feature","bbox":[-84.2817,10.2233,-84.2817,10.2233],"geometry":{"type":"Point","coordinates":[-84.2817,10.2233]},"properties":{"eventtype":"FL","eventid":1102977,"episodeid":1,"eventname":"","glide":"","name":"Flood in Costa Rica","description":"Flood in Costa Rica","htmldescription":"Green Flood in Costa Rica from: 18 Oct 2024 01 to: 20 Oct 2024 01.","icon":"https://www.gdacs.org/images/gdacs_icons/maps/Green/FL.png","iconoverall":"https://www.gdacs.org/images/gdacs_icons/maps/Green/FL.png","url":{"geometry":"https://www.gdacs.org/gdacsapi/api/polygons/getgeometry?eventtype=FL&eventid=1102977&episodeid=1","report":"https://www.gdacs.org/report.aspx?eventid=1102977&episodeid=1&eventtype=FL","details":"https://www.gdacs.org/gdacsapi/api/events/geteventdata?eventtype=FL&eventid=1102977"},"alertlevel":"Green","alertscore":1,"episodealertlevel":"Green","episodealertscore":0.5,"istemporary":"false","iscurrent":"false","country":"Costa Rica","fromdate":"2024-10-18T01:00:00","todate":"2024-10-20T01:00:00","datemodified":"2024-10-26T11:55:33","iso3":"CRI","source":"GLOFAS","sourceid":"","polygonlabel":"Centroid","Class":"Point_Centroid","affectedcountries":[{"iso2":"CR","iso3":"CRI","countryname":"Costa Rica"}],"severitydata":{"severity":0.0,"severitytext":"Magnitude 0 ","severityunit":""}}},{"type":"Feature","bbox":[34.2951,1.1886,34.2951,1.1886],"geometry":{"type":"Point","coordinates":[34.2951,1.1886]},"properties":{"eventtype":"FL","eventid":1102972,"episodeid":1,"eventname":"","glide":"","name":"Flood in Uganda","description":"Flood in Uganda","htmldescription":"Green Flood in Uganda from: 17 Oct 2024 01 to: 19 Oct 2024 01.","icon":"https://www.gdacs.org/images/gdacs_icons/maps/Green/FL.png","iconoverall":"https://www.gdacs.org/images/gdacs_icons/maps/Green/FL.png","url":{"geometry":"https://www.gdacs.org/gdacsapi/api/polygons/getgeometry?eventtype=FL&eventid=1102972&episodeid=1","report":"https://www.gdacs.org/report.aspx?eventid=1102972&episodeid=1&eventtype=FL","details":"https://www.gdacs.org/gdacsapi/api/events/geteventdata?eventtype=FL&eventid=1102972"},"alertlevel":"Green","alertscore":1,"episodealertlevel":"Green","episodealertscore":0.5,"istemporary":"false","iscurrent":"false","country":"Uganda","fromdate":"2024-10-17T01:00:00","todate":"2024-10-19T01:00:00","datemodified":"2024-10-23T05:22:20","iso3":"UGA","source":"GLOFAS","sourceid":"","polygonlabel":"Centroid","Class":"Point_Centroid","affectedcountries":[{"iso2":"UG","iso3":"UGA","countryname":"Uganda"}],"severitydata":{"severity":0.0,"severitytext":"Magnitude 0 ","severityunit":""}}},{"type":"Feature","bbox":[3.5774,6.5269,3.5774,6.5269],"geometry":{"type":"Point","coordinates":[3.5774,6.5269]},"properties":{"eventtype":"FL","eventid":1102970,"episodeid":2,"eventname":"","glide":"","name":"Flood in Nigeria","description":"Flood in Nigeria","htmldescription":"Green Flood in Nigeria from: 14 Oct 2024 01 to: 19 Oct 2024 01.","icon":"https://www.gdacs.org/images/gdacs_icons/maps/Green/FL.png","iconoverall":"https://www.gdacs.org/images/gdacs_icons/maps/Green/FL.png","url":{"geometry":"https://www.gdacs.org/gdacsapi/api/polygons/getgeometry?eventtype=FL&eventid=1102970&episodeid=2","report":"https://www.gdacs.org/report.aspx?eventid=1102970&episodeid=2&eventtype=FL","details":"https://www.gdacs.org/gdacsapi/api/events/geteventdata?eventtype=FL&eventid=1102970"},"alertlevel":"Green","alertscore":1,"episodealertlevel":"Green","episodealertscore":0.5,"istemporary":"false","iscurrent":"false","country":"Nigeria","fromdate":"2024-10-14T01:00:00","todate":"2024-10-19T01:00:00","datemodified":"2024-10-26T12:01:47","iso3":"NGA","source":"GLOFAS","sourceid":"","polygonlabel":"Centroid","Class":"Point_Centroid","affectedcountries":[{"iso2":"NG","iso3":"NGA","countryname":"Nigeria"}],"severitydata":{"severity":0.0,"severitytext":"Magnitude 0 ","severityunit":""}}},{"type":"Feature","bbox":[107.8799,10.8516,107.8799,10.8516],"geometry":{"type":"Point","coordinates":[107.8799,10.8516]},"properties":{"eventtype":"FL","eventid":1102962,"episodeid":2,"eventname":"","glide":"","name":"Flood in Vietnam","description":"Flood in Vietnam","htmldescription":"Green Flood in Vietnam from: 15 Oct 2024 01 to: 18 Oct 2024 01.","icon":"https://www.gdacs.org/images/gdacs_icons/maps/Green/FL.png","iconoverall":"https://www.gdacs.org/images/gdacs_icons/maps/Green/FL.png","url":{"geometry":"https://www.gdacs.org/gdacsapi/api/polygons/getgeometry?eventtype=FL&eventid=1102962&episodeid=2","report":"https://www.gdacs.org/report.aspx?eventid=1102962&episodeid=2&eventtype=FL","details":"https://www.gdacs.org/gdacsapi/api/events/geteventdata?eventtype=FL&eventid=1102962"},"alertlevel":"Green","alertscore":1,"episodealertlevel":"Green","episodealertscore":0.5,"istemporary":"false","iscurrent":"false","country":"Vietnam","fromdate":"2024-10-15T01:00:00","todate":"2024-10-18T01:00:00","datemodified":"2024-10-19T06:35:16","iso3":"VNM","source":"GLOFAS","sourceid":"","polygonlabel":"Centroid","Class":"Point_Centroid","affectedcountries":[{"iso2":"VN","iso3":"VNM","countryname":"Vietnam"}],"severitydata":{"severity":0.0,"severitytext":"Magnitude 0 ","severityunit":""}}},{"type":"Feature","bbox":[14.3788,13.5821,14.3788,13.5821],"geometry":{"type":"Point","coordinates":[14.3788,13.5821]},"properties":{"eventtype":"FL","eventid":1102960,"episodeid":1,"eventname":"","glide":"FL-2024-000191-TCD","name":"Flood in Chad","description":"Flood in Chad","htmldescription":"Orange Flood in Chad from: 01 Sep 2024 12 to: 17 Oct 2024 13.","icon":"https://www.gdacs.org/images/gdacs_icons/maps/Orange/FL.png","iconoverall":"https://www.gdacs.org/images/gdacs_icons/maps/Orange/FL.png","url":{"geometry":"https://www.gdacs.org/gdacsapi/api/polygons/getgeometry?eventtype=FL&eventid=1102960&episodeid=1","report":"https://www.gdacs.org/report.aspx?eventid=1102960&episodeid=1&eventtype=FL","details":"https://www.gdacs.org/gdacsapi/api/events/geteventdata?eventtype=FL&eventid=1102960"},"alertlevel":"Orange","alertscore":2,"episodealertlevel":"Orange","episodealertscore":1.5,"istemporary":"false","iscurrent":"false","country":"Chad","fromdate":"2024-09-01T12:00:00","todate":"2024-10-17T13:00:00","datemodified":"2024-10-17T15:01:36","iso3":"TCD","source":"GLOFAS","sourceid":"","polygonlabel":"Centroid","Class":"Point_Centroid","affectedcountries":[{"iso2":"TD","iso3":"TCD","countryname":"Chad"}],"severitydata":{"severity":0.0,"severitytext":"Magnitude 0 ","severityunit":""}}},{"type":"Feature","bbox":[59.5297,22.5694,59.5297,22.5694],"geometry":{"type":"Point","coordinates":[59.5297,22.5694]},"properties":{"eventtype":"FL","eventid":1102956,"episodeid":1,"eventname":"","glide":"","name":"Flood in Oman","description":"Flood in Oman","htmldescription":"Green Flood in Oman from: 15 Oct 2024 01 to: 17 Oct 2024 01.","icon":"https://www.gdacs.org/images/gdacs_icons/maps/Green/FL.png","iconoverall":"https://www.gdacs.org/images/gdacs_icons/maps/Green/FL.png","url":{"geometry":"https://www.gdacs.org/gdacsapi/api/polygons/getgeometry?eventtype=FL&eventid=1102956&episodeid=1","report":"https://www.gdacs.org/report.aspx?eventid=1102956&episodeid=1&eventtype=FL","details":"https://www.gdacs.org/gdacsapi/api/events/geteventdata?eventtype=FL&eventid=1102956"},"alertlevel":"Green","alertscore":1,"episodealertlevel":"Green","episodealertscore":0.5,"istemporary":"false","iscurrent":"false","country":"Oman","fromdate":"2024-10-15T01:00:00","todate":"2024-10-17T01:00:00","datemodified":"2024-10-17T05:42:09","iso3":"OMN","source":"GLOFAS","sourceid":"","polygonlabel":"Centroid","Class":"Point_Centroid","affectedcountries":[{"iso2":"OM","iso3":"OMN","countryname":"Oman"}],"severitydata":{"severity":0.0,"severitytext":"Magnitude 0 ","severityunit":""}}},{"type":"Feature","bbox":[-4.0683,34.3584,-4.0683,34.3584],"geometry":{"type":"Point","coordinates":[-4.0683,34.3584]},"properties":{"eventtype":"FL","eventid":1102953,"episodeid":1,"eventname":"","glide":"","name":"Flood in Morocco","description":"Flood in Morocco","htmldescription":"Green Flood in Morocco from: 12 Oct 2024 01 to: 14 Oct 2024 01.","icon":"https://www.gdacs.org/images/gdacs_icons/maps/Green/FL.png","iconoverall":"https://www.gdacs.org/images/gdacs_icons/maps/Green/FL.png","url":{"geometry":"https://www.gdacs.org/gdacsapi/api/polygons/getgeometry?eventtype=FL&eventid=1102953&episodeid=1","report":"https://www.gdacs.org/report.aspx?eventid=1102953&episodeid=1&eventtype=FL","details":"https://www.gdacs.org/gdacsapi/api/events/geteventdata?eventtype=FL&eventid=1102953"},"alertlevel":"Green","alertscore":1,"episodealertlevel":"Green","episodealertscore":0.5,"istemporary":"false","iscurrent":"false","country":"Morocco","fromdate":"2024-10-12T01:00:00","todate":"2024-10-14T01:00:00","datemodified":"2024-10-16T08:33:46","iso3":"MAR","source":"GLOFAS","sourceid":"","polygonlabel":"Centroid","Class":"Point_Centroid","affectedcountries":[{"iso2":"MA","iso3":"MAR","countryname":"Morocco"}],"severitydata":{"severity":0.0,"severitytext":"Magnitude 0 ","severityunit":""}}},{"type":"Feature","bbox":[1.2158,6.1304,1.2158,6.1304],"geometry":{"type":"Point","coordinates":[1.2158,6.1304]},"properties":{"eventtype":"FL","eventid":1102954,"episodeid":1,"eventname":"","glide":"","name":"Flood in Togo","description":"Flood in Togo","htmldescription":"Green Flood in Togo from: 12 Oct 2024 01 to: 14 Oct 2024 01.","icon":"https://www.gdacs.org/images/gdacs_icons/maps/Green/FL.png","iconoverall":"https://www.gdacs.org/images/gdacs_icons/maps/Green/FL.png","url":{"geometry":"https://www.gdacs.org/gdacsapi/api/polygons/getgeometry?eventtype=FL&eventid=1102954&episodeid=1","report":"https://www.gdacs.org/report.aspx?eventid=1102954&episodeid=1&eventtype=FL","details":"https://www.gdacs.org/gdacsapi/api/events/geteventdata?eventtype=FL&eventid=1102954"},"alertlevel":"Green","alertscore":1,"episodealertlevel":"Green","episodealertscore":0.5,"istemporary":"false","iscurrent":"false","country":"Togo","fromdate":"2024-10-12T01:00:00","todate":"2024-10-14T01:00:00","datemodified":"2024-10-16T08:35:12","iso3":"TGO","source":"GLOFAS","sourceid":"","polygonlabel":"Centroid","Class":"Point_Centroid","affectedcountries":[{"iso2":"TG","iso3":"TGO","countryname":"Togo"}],"severitydata":{"severity":0.0,"severitytext":"Magnitude 0 ","severityunit":""}}},{"type":"Feature","bbox":[-9.2399,20.254,-9.2399,20.254],"geometry":{"type":"Point","coordinates":[-9.2399,20.254]},"properties":{"eventtype":"FL","eventid":1102958,"episodeid":1,"eventname":"","glide":"","name":"Flood in Mauritania","description":"Flood in Mauritania","htmldescription":"Green Flood in Mauritania from: 10 Oct 2024 01 to: 12 Oct 2024 01.","icon":"https://www.gdacs.org/images/gdacs_icons/maps/Green/FL.png","iconoverall":"https://www.gdacs.org/images/gdacs_icons/maps/Green/FL.png","url":{"geometry":"https://www.gdacs.org/gdacsapi/api/polygons/getgeometry?eventtype=FL&eventid=1102958&episodeid=1","report":"https://www.gdacs.org/report.aspx?eventid=1102958&episodeid=1&eventtype=FL","details":"https://www.gdacs.org/gdacsapi/api/events/geteventdata?eventtype=FL&eventid=1102958"},"alertlevel":"Green","alertscore":1,"episodealertlevel":"Green","episodealertscore":0.5,"istemporary":"false","iscurrent":"false","country":"Mauritania","fromdate":"2024-10-10T01:00:00","todate":"2024-10-12T01:00:00","datemodified":"2024-10-17T06:52:09","iso3":"MRT","source":"GLOFAS","sourceid":"","polygonlabel":"Centroid","Class":"Point_Centroid","affectedcountries":[{"iso2":"MR","iso3":"MRT","countryname":"Mauritania"}],"severitydata":{"severity":0.0,"severitytext":"Magnitude 0 ","severityunit":""}}},{"type":"Feature","bbox":[-81.464,27.7568,-81.464,27.7568],"geometry":{"type":"Point","coordinates":[-81.464,27.7568]},"properties":{"eventtype":"FL","eventid":1102949,"episodeid":1,"eventname":"","glide":"","name":"Flood in United States","description":"Flood in United States","htmldescription":"Green Flood in United States from: 09 Oct 2024 01 to: 11 Oct 2024 01.","icon":"https://www.gdacs.org/images/gdacs_icons/maps/Green/FL.png","iconoverall":"https://www.gdacs.org/images/gdacs_icons/maps/Green/FL.png","url":{"geometry":"https://www.gdacs.org/gdacsapi/api/polygons/getgeometry?eventtype=FL&eventid=1102949&episodeid=1","report":"https://www.gdacs.org/report.aspx?eventid=1102949&episodeid=1&eventtype=FL","details":"https://www.gdacs.org/gdacsapi/api/events/geteventdata?eventtype=FL&eventid=1102949"},"alertlevel":"Green","alertscore":1,"episodealertlevel":"Green","episodealertscore":0.5,"istemporary":"false","iscurrent":"false","country":"United States","fromdate":"2024-10-09T01:00:00","todate":"2024-10-11T01:00:00","datemodified":"2024-10-11T11:32:16","iso3":"USA","source":"GLOFAS","sourceid":"","polygonlabel":"Centroid","Class":"Point_Centroid","affectedcountries":[{"iso2":"US","iso3":"USA","countryname":"United States"}],"severitydata":{"severity":0.0,"severitytext":"Magnitude 0 ","severityunit":""}}},{"type":"Feature","bbox":[4.4955,50.0525,4.4955,50.0525],"geometry":{"type":"Point","coordinates":[4.4955,50.0525]},"properties":{"eventtype":"FL","eventid":1102951,"episodeid":1,"eventname":"","glide":"","name":"Flood in Belgium","description":"Flood in Belgium","htmldescription":"Green Flood in Belgium from: 09 Oct 2024 01 to: 11 Oct 2024 01.","icon":"https://www.gdacs.org/images/gdacs_icons/maps/Green/FL.png","iconoverall":"https://www.gdacs.org/images/gdacs_icons/maps/Green/FL.png","url":{"geometry":"https://www.gdacs.org/gdacsapi/api/polygons/getgeometry?eventtype=FL&eventid=1102951&episodeid=1","report":"https://www.gdacs.org/report.aspx?eventid=1102951&episodeid=1&eventtype=FL","details":"https://www.gdacs.org/gdacsapi/api/events/geteventdata?eventtype=FL&eventid=1102951"},"alertlevel":"Green","alertscore":1,"episodealertlevel":"Green","episodealertscore":0.5,"istemporary":"false","iscurrent":"false","country":"Belgium","fromdate":"2024-10-09T01:00:00","todate":"2024-10-11T01:00:00","datemodified":"2024-10-14T06:22:13","iso3":"BEL","source":"GLOFAS","sourceid":"","polygonlabel":"Centroid","Class":"Point_Centroid","affectedcountries":[{"iso2":"BE","iso3":"BEL","countryname":"Belgium"}],"severitydata":{"severity":0.0,"severitytext":"Magnitude 0 ","severityunit":""}}},{"type":"Feature","bbox":[71.2679,33.7128,71.2679,33.7128],"geometry":{"type":"Point","coordinates":[71.2679,33.7128]},"properties":{"eventtype":"FL","eventid":1102947,"episodeid":1,"eventname":"","glide":"","name":"Flood in Pakistan","description":"Flood in Pakistan","htmldescription":"Green Flood in Pakistan from: 07 Oct 2024 01 to: 10 Oct 2024 01.","icon":"https://www.gdacs.org/images/gdacs_icons/maps/Green/FL.png","iconoverall":"https://www.gdacs.org/images/gdacs_icons/maps/Green/FL.png","url":{"geometry":"https://www.gdacs.org/gdacsapi/api/polygons/getgeometry?eventtype=FL&eventid=1102947&episodeid=1","report":"https://www.gdacs.org/report.aspx?eventid=1102947&episodeid=1&eventtype=FL","details":"https://www.gdacs.org/gdacsapi/api/events/geteventdata?eventtype=FL&eventid=1102947"},"alertlevel":"Green","alertscore":1,"episodealertlevel":"Green","episodealertscore":0.5,"istemporary":"false","iscurrent":"false","country":"Pakistan","fromdate":"2024-10-07T01:00:00","todate":"2024-10-10T01:00:00","datemodified":"2024-10-11T05:52:13","iso3":"PAK","source":"GLOFAS","sourceid":"","polygonlabel":"Centroid","Class":"Point_Centroid","affectedcountries":[{"iso2":"PK","iso3":"PAK","countryname":"Pakistan"}],"severitydata":{"severity":0.0,"severitytext":"Magnitude 0 ","severityunit":""}}},{"type":"Feature","bbox":[-69.1867,-12.5939,-69.1867,-12.5939],"geometry":{"type":"Point","coordinates":[-69.1867,-12.5939]},"properties":{"eventtype":"FL","eventid":1102948,"episodeid":1,"eventname":"","glide":"","name":"Flood in Peru","description":"Flood in Peru","htmldescription":"Green Flood in Peru from: 09 Oct 2024 01 to: 10 Oct 2024 01.","icon":"https://www.gdacs.org/images/gdacs_icons/maps/Green/FL.png","iconoverall":"https://www.gdacs.org/images/gdacs_icons/maps/Green/FL.png","url":{"geometry":"https://www.gdacs.org/gdacsapi/api/polygons/getgeometry?eventtype=FL&eventid=1102948&episodeid=1","report":"https://www.gdacs.org/report.aspx?eventid=1102948&episodeid=1&eventtype=FL","details":"https://www.gdacs.org/gdacsapi/api/events/geteventdata?eventtype=FL&eventid=1102948"},"alertlevel":"Green","alertscore":1,"episodealertlevel":"Green","episodealertscore":0.5,"istemporary":"false","iscurrent":"false","country":"Peru","fromdate":"2024-10-09T01:00:00","todate":"2024-10-10T01:00:00","datemodified":"2024-10-11T11:22:12","iso3":"PER","source":"GLOFAS","sourceid":"","polygonlabel":"Centroid","Class":"Point_Centroid","affectedcountries":[{"iso2":"PE","iso3":"PER","countryname":"Peru"}],"severitydata":{"severity":0.0,"severitytext":"Magnitude 0 ","severityunit":""}}},{"type":"Feature","bbox":[80.7138,7.5555,80.7138,7.5555],"geometry":{"type":"Point","coordinates":[80.7138,7.5555]},"properties":{"eventtype":"FL","eventid":1102957,"episodeid":1,"eventname":"","glide":"","name":"Flood in Sri Lanka","description":"Flood in Sri Lanka","htmldescription":"Green Flood in Sri Lanka from: 08 Oct 2024 01 to: 10 Oct 2024 01.","icon":"https://www.gdacs.org/images/gdacs_icons/maps/Green/FL.png","iconoverall":"https://www.gdacs.org/images/gdacs_icons/maps/Green/FL.png","url":{"geometry":"https://www.gdacs.org/gdacsapi/api/polygons/getgeometry?eventtype=FL&eventid=1102957&episodeid=1","report":"https://www.gdacs.org/report.aspx?eventid=1102957&episodeid=1&eventtype=FL","details":"https://www.gdacs.org/gdacsapi/api/events/geteventdata?eventtype=FL&eventid=1102957"},"alertlevel":"Green","alertscore":1,"episodealertlevel":"Green","episodealertscore":0.5,"istemporary":"false","iscurrent":"false","country":"Sri Lanka","fromdate":"2024-10-08T01:00:00","todate":"2024-10-10T01:00:00","datemodified":"2024-10-17T05:43:39","iso3":"LKA","source":"GLOFAS","sourceid":"","polygonlabel":"Centroid","Class":"Point_Centroid","affectedcountries":[{"iso2":"LK","iso3":"LKA","countryname":"Sri Lanka"}],"severitydata":{"severity":0.0,"severitytext":"Magnitude 0 ","severityunit":""}}},{"type":"Feature","bbox":[9.718,45.6844,9.718,45.6844],"geometry":{"type":"Point","coordinates":[9.718,45.6844]},"properties":{"eventtype":"FL","eventid":1102833,"episodeid":22,"eventname":"","glide":"","name":"Flood in Italy","description":"Flood in Italy","htmldescription":"Green Flood in Italy from: 14 Aug 2024 01 to: 10 Oct 2024 01.","icon":"https://www.gdacs.org/images/gdacs_icons/maps/Green/FL.png","iconoverall":"https://www.gdacs.org/images/gdacs_icons/maps/Green/FL.png","url":{"geometry":"https://www.gdacs.org/gdacsapi/api/polygons/getgeometry?eventtype=FL&eventid=1102833&episodeid=22","report":"https://www.gdacs.org/report.aspx?eventid=1102833&episodeid=22&eventtype=FL","details":"https://www.gdacs.org/gdacsapi/api/events/geteventdata?eventtype=FL&eventid=1102833"},"alertlevel":"Green","alertscore":1,"episodealertlevel":"Green","episodealertscore":0.5,"istemporary":"false","iscurrent":"false","country":"Italy","fromdate":"2024-08-14T01:00:00","todate":"2024-10-10T01:00:00","datemodified":"2024-10-12T07:23:38","iso3":"ITA","source":"GLOFAS","sourceid":"","polygonlabel":"Centroid","Class":"Point_Centroid","affectedcountries":[{"iso2":"IT","iso3":"ITA","countryname":"Italy"}],"severitydata":{"severity":0.0,"severitytext":"Magnitude 0 ","severityunit":""}}},{"type":"Feature","bbox":[-1.688,12.0753,-1.688,12.0753],"geometry":{"type":"Point","coordinates":[-1.688,12.0753]},"properties":{"eventtype":"FL","eventid":1102943,"episodeid":2,"eventname":"","glide":"","name":"Flood in Burkina Faso","description":"Flood in Burkina Faso","htmldescription":"Green Flood in Burkina Faso from: 01 Sep 2024 01 to: 09 Oct 2024 01.","icon":"https://www.gdacs.org/images/gdacs_icons/maps/Green/FL.png","iconoverall":"https://www.gdacs.org/images/gdacs_icons/maps/Green/FL.png","url":{"geometry":"https://www.gdacs.org/gdacsapi/api/polygons/getgeometry?eventtype=FL&eventid=1102943&episodeid=2","report":"https://www.gdacs.org/report.aspx?eventid=1102943&episodeid=2&eventtype=FL","details":"https://www.gdacs.org/gdacsapi/api/events/geteventdata?eventtype=FL&eventid=1102943"},"alertlevel":"Green","alertscore":1,"episodealertlevel":"Green","episodealertscore":0.5,"istemporary":"false","iscurrent":"false","country":"Burkina Faso","fromdate":"2024-09-01T01:00:00","todate":"2024-10-09T01:00:00","datemodified":"2024-10-16T08:32:15","iso3":"BFA","source":"GLOFAS","sourceid":"","polygonlabel":"Centroid","Class":"Point_Centroid","affectedcountries":[{"iso2":"BF","iso3":"BFA","countryname":"Burkina Faso"}],"severitydata":{"severity":0.0,"severitytext":"Magnitude 0 ","severityunit":""}}},{"type":"Feature","bbox":[100.6715,5.8098,100.6715,5.8098],"geometry":{"type":"Point","coordinates":[100.6715,5.8098]},"properties":{"eventtype":"FL","eventid":1102946,"episodeid":1,"eventname":"","glide":"","name":"Flood in Malaysia","description":"Flood in Malaysia","htmldescription":"Green Flood in Malaysia from: 07 Oct 2024 01 to: 09 Oct 2024 01.","icon":"https://www.gdacs.org/images/gdacs_icons/maps/Green/FL.png","iconoverall":"https://www.gdacs.org/images/gdacs_icons/maps/Green/FL.png","url":{"geometry":"https://www.gdacs.org/gdacsapi/api/polygons/getgeometry?eventtype=FL&eventid=1102946&episodeid=1","report":"https://www.gdacs.org/report.aspx?eventid=1102946&episodeid=1&eventtype=FL","details":"https://www.gdacs.org/gdacsapi/api/events/geteventdata?eventtype=FL&eventid=1102946"},"alertlevel":"Green","alertscore":1,"episodealertlevel":"Green","episodealertscore":0.5,"istemporary":"false","iscurrent":"false","country":"Malaysia","fromdate":"2024-10-07T01:00:00","todate":"2024-10-09T01:00:00","datemodified":"2024-10-10T07:13:54","iso3":"MYS","source":"GLOFAS","sourceid":"","polygonlabel":"Centroid","Class":"Point_Centroid","affectedcountries":[{"iso2":"MY","iso3":"MYS","countryname":"Malaysia"}],"severitydata":{"severity":0.0,"severitytext":"Magnitude 0 ","severityunit":""}}},{"type":"Feature","bbox":[-61.2202,-3.337,-61.2202,-3.337],"geometry":{"type":"Point","coordinates":[-61.2202,-3.337]},"properties":{"eventtype":"FL","eventid":1102944,"episodeid":1,"eventname":"","glide":"","name":"Flood in Brazil","description":"Flood in Brazil","htmldescription":"Green Flood in Brazil from: 07 Oct 2024 01 to: 08 Oct 2024 01.","icon":"https://www.gdacs.org/images/gdacs_icons/maps/Green/FL.png","iconoverall":"https://www.gdacs.org/images/gdacs_icons/maps/Green/FL.png","url":{"geometry":"https://www.gdacs.org/gdacsapi/api/polygons/getgeometry?eventtype=FL&eventid=1102944&episodeid=1","report":"https://www.gdacs.org/report.aspx?eventid=1102944&episodeid=1&eventtype=FL","details":"https://www.gdacs.org/gdacsapi/api/events/geteventdata?eventtype=FL&eventid=1102944"},"alertlevel":"Green","alertscore":1,"episodealertlevel":"Green","episodealertscore":0.5,"istemporary":"false","iscurrent":"false","country":"Brazil","fromdate":"2024-10-07T01:00:00","todate":"2024-10-08T01:00:00","datemodified":"2024-10-09T07:52:06","iso3":"BRA","source":"GLOFAS","sourceid":"","polygonlabel":"Centroid","Class":"Point_Centroid","affectedcountries":[{"iso2":"BR","iso3":"BRA","countryname":"Brazil"}],"severitydata":{"severity":0.0,"severitytext":"Magnitude 0 ","severityunit":""}}},{"type":"Feature","bbox":[75.8303,14.2559,75.8303,14.2559],"geometry":{"type":"Point","coordinates":[75.8303,14.2559]},"properties":{"eventtype":"FL","eventid":1102945,"episodeid":5,"eventname":"","glide":"","name":"Flood in India","description":"Flood in India","htmldescription":"Green Flood in India from: 20 Sep 2024 01 to: 07 Oct 2024 01.","icon":"https://www.gdacs.org/images/gdacs_icons/maps/Green/FL.png","iconoverall":"https://www.gdacs.org/images/gdacs_icons/maps/Green/FL.png","url":{"geometry":"https://www.gdacs.org/gdacsapi/api/polygons/getgeometry?eventtype=FL&eventid=1102945&episodeid=5","report":"https://www.gdacs.org/report.aspx?eventid=1102945&episodeid=5&eventtype=FL","details":"https://www.gdacs.org/gdacsapi/api/events/geteventdata?eventtype=FL&eventid=1102945"},"alertlevel":"Green","alertscore":1,"episodealertlevel":"Green","episodealertscore":0.5,"istemporary":"false","iscurrent":"false","country":"India","fromdate":"2024-09-20T01:00:00","todate":"2024-10-07T01:00:00","datemodified":"2024-10-10T07:12:10","iso3":"IND","source":"GLOFAS","sourceid":"","polygonlabel":"Centroid","Class":"Point_Centroid","affectedcountries":[{"iso2":"IN","iso3":"IND","countryname":"India"}],"severitydata":{"severity":0.0,"severitytext":"Magnitude 0 ","severityunit":""}}},{"type":"Feature","bbox":[106.0083,10.2327,106.0083,10.2327],"geometry":{"type":"Point","coordinates":[106.0083,10.2327]},"properties":{"eventtype":"FL","eventid":1102926,"episodeid":2,"eventname":"","glide":"","name":"Flood in Vietnam","description":"Flood in Vietnam","htmldescription":"Green Flood in Vietnam from: 29 Sep 2024 01 to: 07 Oct 2024 01.","icon":"https://www.gdacs.org/images/gdacs_icons/maps/Green/FL.png","iconoverall":"https://www.gdacs.org/images/gdacs_icons/maps/Green/FL.png","url":{"geometry":"https://www.gdacs.org/gdacsapi/api/polygons/getgeometry?eventtype=FL&eventid=1102926&episodeid=2","report":"https://www.gdacs.org/report.aspx?eventid=1102926&episodeid=2&eventtype=FL","details":"https://www.gdacs.org/gdacsapi/api/events/geteventdata?eventtype=FL&eventid=1102926"},"alertlevel":"Green","alertscore":1,"episodealertlevel":"Green","episodealertscore":0.5,"istemporary":"false","iscurrent":"false","country":"Vietnam","fromdate":"2024-09-29T01:00:00","todate":"2024-10-07T01:00:00","datemodified":"2024-10-11T05:53:44","iso3":"VNM","source":"GLOFAS","sourceid":"","polygonlabel":"Centroid","Class":"Point_Centroid","affectedcountries":[{"iso2":"VN","iso3":"VNM","countryname":"Vietnam"}],"severitydata":{"severity":0.0,"severitytext":"Magnitude 0 ","severityunit":""}}},{"type":"Feature","bbox":[90.2934,24.4769,90.2934,24.4769],"geometry":{"type":"Point","coordinates":[90.2934,24.4769]},"properties":{"eventtype":"FL","eventid":1102937,"episodeid":1,"eventname":"","glide":"","name":"Flood in Bangladesh","description":"Flood in Bangladesh","htmldescription":"Green Flood in Bangladesh from: 05 Oct 2024 01 to: 07 Oct 2024 01.","icon":"https://www.gdacs.org/images/gdacs_icons/maps/Green/FL.png","iconoverall":"https://www.gdacs.org/images/gdacs_icons/maps/Green/FL.png","url":{"geometry":"https://www.gdacs.org/gdacsapi/api/polygons/getgeometry?eventtype=FL&eventid=1102937&episodeid=1","report":"https://www.gdacs.org/report.aspx?eventid=1102937&episodeid=1&eventtype=FL","details":"https://www.gdacs.org/gdacsapi/api/events/geteventdata?eventtype=FL&eventid=1102937"},"alertlevel":"Green","alertscore":1,"episodealertlevel":"Green","episodealertscore":0.5,"istemporary":"false","iscurrent":"false","country":"Bangladesh","fromdate":"2024-10-05T01:00:00","todate":"2024-10-07T01:00:00","datemodified":"2024-10-08T05:52:22","iso3":"BGD","source":"GLOFAS","sourceid":"","polygonlabel":"Centroid","Class":"Point_Centroid","affectedcountries":[{"iso2":"BD","iso3":"BGD","countryname":"Bangladesh"}],"severitydata":{"severity":0.0,"severitytext":"Magnitude 0 ","severityunit":""}}},{"type":"Feature","bbox":[-9.4524,51.6798,-9.4524,51.6798],"geometry":{"type":"Point","coordinates":[-9.4524,51.6798]},"properties":{"eventtype":"FL","eventid":1102939,"episodeid":1,"eventname":"","glide":"","name":"Flood in Ireland","description":"Flood in Ireland","htmldescription":"Green Flood in Ireland from: 05 Oct 2024 01 to: 07 Oct 2024 01.","icon":"https://www.gdacs.org/images/gdacs_icons/maps/Green/FL.png","iconoverall":"https://www.gdacs.org/images/gdacs_icons/maps/Green/FL.png","url":{"geometry":"https://www.gdacs.org/gdacsapi/api/polygons/getgeometry?eventtype=FL&eventid=1102939&episodeid=1","report":"https://www.gdacs.org/report.aspx?eventid=1102939&episodeid=1&eventtype=FL","details":"https://www.gdacs.org/gdacsapi/api/events/geteventdata?eventtype=FL&eventid=1102939"},"alertlevel":"Green","alertscore":1,"episodealertlevel":"Green","episodealertscore":0.5,"istemporary":"false","iscurrent":"false","country":"Ireland","fromdate":"2024-10-05T01:00:00","todate":"2024-10-07T01:00:00","datemodified":"2024-10-08T07:53:47","iso3":"IRL","source":"GLOFAS","sourceid":"","polygonlabel":"Centroid","Class":"Point_Centroid","affectedcountries":[{"iso2":"IE","iso3":"IRL","countryname":"Ireland"}],"severitydata":{"severity":0.0,"severitytext":"Magnitude 0 ","severityunit":""}}},{"type":"Feature","bbox":[21.249,38.7033,21.249,38.7033],"geometry":{"type":"Point","coordinates":[21.249,38.7033]},"properties":{"eventtype":"FL","eventid":1102940,"episodeid":1,"eventname":"","glide":"","name":"Flood in Greece","description":"Flood in Greece","htmldescription":"Green Flood in Greece from: 04 Oct 2024 01 to: 06 Oct 2024 01.","icon":"https://www.gdacs.org/images/gdacs_icons/maps/Green/FL.png","iconoverall":"https://www.gdacs.org/images/gdacs_icons/maps/Green/FL.png","url":{"geometry":"https://www.gdacs.org/gdacsapi/api/polygons/getgeometry?eventtype=FL&eventid=1102940&episodeid=1","report":"https://www.gdacs.org/report.aspx?eventid=1102940&episodeid=1&eventtype=FL","details":"https://www.gdacs.org/gdacsapi/api/events/geteventdata?eventtype=FL&eventid=1102940"},"alertlevel":"Green","alertscore":1,"episodealertlevel":"Green","episodealertscore":0.5,"istemporary":"false","iscurrent":"false","country":"Greece","fromdate":"2024-10-04T01:00:00","todate":"2024-10-06T01:00:00","datemodified":"2024-10-08T09:23:09","iso3":"GRC","source":"GLOFAS","sourceid":"","polygonlabel":"Centroid","Class":"Point_Centroid","affectedcountries":[{"iso2":"GR","iso3":"GRC","countryname":"Greece"}],"severitydata":{"severity":0.0,"severitytext":"Magnitude 0 ","severityunit":""}}},{"type":"Feature","bbox":[120.982,23.9739,120.982,23.9739],"geometry":{"type":"Point","coordinates":[120.982,23.9739]},"properties":{"eventtype":"FL","eventid":1102938,"episodeid":1,"eventname":"","glide":"","name":"Flood in Taiwan","description":"Flood in Taiwan","htmldescription":"Green Flood in Taiwan from: 03 Oct 2024 01 to: 06 Oct 2024 01.","icon":"https://www.gdacs.org/images/gdacs_icons/maps/Green/FL.png","iconoverall":"https://www.gdacs.org/images/gdacs_icons/maps/Green/FL.png","url":{"geometry":"https://www.gdacs.org/gdacsapi/api/polygons/getgeometry?eventtype=FL&eventid=1102938&episodeid=1","report":"https://www.gdacs.org/report.aspx?eventid=1102938&episodeid=1&eventtype=FL","details":"https://www.gdacs.org/gdacsapi/api/events/geteventdata?eventtype=FL&eventid=1102938"},"alertlevel":"Green","alertscore":1,"episodealertlevel":"Green","episodealertscore":0.5,"istemporary":"false","iscurrent":"false","country":"Taiwan","fromdate":"2024-10-03T01:00:00","todate":"2024-10-06T01:00:00","datemodified":"2024-10-08T05:57:24","iso3":"TWN","source":"GLOFAS","sourceid":"","polygonlabel":"Centroid","Class":"Point_Centroid","affectedcountries":[{"iso2":"TW","iso3":"TWN","countryname":"Taiwan"}],"severitydata":{"severity":0.0,"severitytext":"Magnitude 0 ","severityunit":""}}},{"type":"Feature","bbox":[19.4913,40.4708,19.4913,40.4708],"geometry":{"type":"Point","coordinates":[19.4913,40.4708]},"properties":{"eventtype":"FL","eventid":1102934,"episodeid":1,"eventname":"","glide":"","name":"Flood in Albania, The Republic of North Macedonia","description":"Flood in Albania, The Republic of North Macedonia","htmldescription":"Green Flood in Albania, The Republic of North Macedonia from: 04 Oct 2024 01 to: 06 Oct 2024 01.","icon":"https://www.gdacs.org/images/gdacs_icons/maps/Green/FL.png","iconoverall":"https://www.gdacs.org/images/gdacs_icons/maps/Green/FL.png","url":{"geometry":"https://www.gdacs.org/gdacsapi/api/polygons/getgeometry?eventtype=FL&eventid=1102934&episodeid=1","report":"https://www.gdacs.org/report.aspx?eventid=1102934&episodeid=1&eventtype=FL","details":"https://www.gdacs.org/gdacsapi/api/events/geteventdata?eventtype=FL&eventid=1102934"},"alertlevel":"Green","alertscore":1,"episodealertlevel":"Green","episodealertscore":0.5,"istemporary":"false","iscurrent":"false","country":"Albania, The Republic of North Macedonia","fromdate":"2024-10-04T01:00:00","todate":"2024-10-06T01:00:00","datemodified":"2024-10-07T05:51:13","iso3":"ALB","source":"GLOFAS","sourceid":"","polygonlabel":"Centroid","Class":"Point_Centroid","affectedcountries":[{"iso2":"AL","iso3":"ALB","countryname":"Albania"},{"iso2":"MK","iso3":"MKD","countryname":"The Republic of North Macedonia"}],"severitydata":{"severity":0.0,"severitytext":"Magnitude 0 ","severityunit":""}}},{"type":"Feature","bbox":[19.5181,42.9869,19.5181,42.9869],"geometry":{"type":"Point","coordinates":[19.5181,42.9869]},"properties":{"eventtype":"FL","eventid":1102935,"episodeid":1,"eventname":"","glide":"","name":"Flood in Montenegro","description":"Flood in Montenegro","htmldescription":"Green Flood in Montenegro from: 04 Oct 2024 01 to: 06 Oct 2024 01.","icon":"https://www.gdacs.org/images/gdacs_icons/maps/Green/FL.png","iconoverall":"https://www.gdacs.org/images/gdacs_icons/maps/Green/FL.png","url":{"geometry":"https://www.gdacs.org/gdacsapi/api/polygons/getgeometry?eventtype=FL&eventid=1102935&episodeid=1","report":"https://www.gdacs.org/report.aspx?eventid=1102935&episodeid=1&eventtype=FL","details":"https://www.gdacs.org/gdacsapi/api/events/geteventdata?eventtype=FL&eventid=1102935"},"alertlevel":"Green","alertscore":1,"episodealertlevel":"Green","episodealertscore":0.5,"istemporary":"false","iscurrent":"false","country":"Montenegro","fromdate":"2024-10-04T01:00:00","todate":"2024-10-06T01:00:00","datemodified":"2025-08-14T10:20:41.9","iso3":"MNE","source":"GLOFAS","sourceid":"","polygonlabel":"Centroid","Class":"Point_Centroid","affectedcountries":[{"iso2":"ME","iso3":"MNE","countryname":"Montenegro"}],"severitydata":{"severity":0.0,"severitytext":"Magnitude 0 ","severityunit":""}}},{"type":"Feature","bbox":[170.5036,-45.8741,170.5036,-45.8741],"geometry":{"type":"Point","coordinates":[170.5036,-45.8741]},"properties":{"eventtype":"FL","eventid":1102932,"episodeid":1,"eventname":"","glide":"","name":"Flood in New Zealand","description":"Flood in New Zealand","htmldescription":"Green Flood in New Zealand from: 03 Oct 2024 01 to: 05 Oct 2024 01.","icon":"https://www.gdacs.org/images/gdacs_icons/maps/Green/FL.png","iconoverall":"https://www.gdacs.org/images/gdacs_icons/maps/Green/FL.png","url":{"geometry":"https://www.gdacs.org/gdacsapi/api/polygons/getgeometry?eventtype=FL&eventid=1102932&episodeid=1","report":"https://www.gdacs.org/report.aspx?eventid=1102932&episodeid=1&eventtype=FL","details":"https://www.gdacs.org/gdacsapi/api/events/geteventdata?eventtype=FL&eventid=1102932"},"alertlevel":"Green","alertscore":1,"episodealertlevel":"Green","episodealertscore":0.5,"istemporary":"false","iscurrent":"false","country":"New Zealand","fromdate":"2024-10-03T01:00:00","todate":"2024-10-05T01:00:00","datemodified":"2024-10-05T06:31:09","iso3":"NZL","source":"GLOFAS","sourceid":"","polygonlabel":"Centroid","Class":"Point_Centroid","affectedcountries":[{"iso2":"NZ","iso3":"NZL","countryname":"New Zealand"}],"severitydata":{"severity":0.0,"severitytext":"Magnitude 0 ","severityunit":""}}},{"type":"Feature","bbox":[17.0022,45.118,17.0022,45.118],"geometry":{"type":"Point","coordinates":[17.0022,45.118]},"properties":{"eventtype":"FL","eventid":1102933,"episodeid":1,"eventname":"","glide":"","name":"Flood in Bosnia  and  Herzegovina","description":"Flood in Bosnia  and  Herzegovina","htmldescription":"Orange Flood in Bosnia  and  Herzegovina from: 03 Oct 2024 01 to: 05 Oct 2024 01.","icon":"https://www.gdacs.org/images/gdacs_icons/maps/Orange/FL.png","iconoverall":"https://www.gdacs.org/images/gdacs_icons/maps/Orange/FL.png","url":{"geometry":"https://www.gdacs.org/gdacsapi/api/polygons/getgeometry?eventtype=FL&eventid=1102933&episodeid=1","report":"https://www.gdacs.org/report.aspx?eventid=1102933&episodeid=1&eventtype=FL","details":"https://www.gdacs.org/gdacsapi/api/events/geteventdata?eventtype=FL&eventid=1102933"},"alertlevel":"Orange","alertscore":2,"episodealertlevel":"Orange","episodealertscore":1.5,"istemporary":"false","iscurrent":"false","country":"Bosnia & Herzegovina","fromdate":"2024-10-03T01:00:00","todate":"2024-10-05T01:00:00","datemodified":"2024-10-05T07:11:04","iso3":"BIH","source":"GLOFAS","sourceid":"","polygonlabel":"Centroid","Class":"Point_Centroid","affectedcountries":[{"iso2":"BA","iso3":"BIH","countryname":"Bosnia & Herzegovina"}],"severitydata":{"severity":0.0,"severitytext":"Magnitude 0 ","severityunit":""}}},{"type":"Feature","bbox":[-6.5928,5.7853,-6.5928,5.7853],"geometry":{"type":"Point","coordinates":[-6.5928,5.7853]},"properties":{"eventtype":"FL","eventid":1102966,"episodeid":1,"eventname":"","glide":"","name":"Flood in Cote d'Ivoire","description":"Flood in Cote d'Ivoire","htmldescription":"Green Flood in Cote d'Ivoire from: 03 Oct 2024 01 to: 05 Oct 2024 01.","icon":"https://www.gdacs.org/images/gdacs_icons/maps/Green/FL.png","iconoverall":"https://www.gdacs.org/images/gdacs_icons/maps/Green/FL.png","url":{"geometry":"https://www.gdacs.org/gdacsapi/api/polygons/getgeometry?eventtype=FL&eventid=1102966&episodeid=1","report":"https://www.gdacs.org/report.aspx?eventid=1102966&episodeid=1&eventtype=FL","details":"https://www.gdacs.org/gdacsapi/api/events/geteventdata?eventtype=FL&eventid=1102966"},"alertlevel":"Green","alertscore":1,"episodealertlevel":"Green","episodealertscore":0.5,"istemporary":"false","iscurrent":"false","country":"Cote d'Ivoire","fromdate":"2024-10-03T01:00:00","todate":"2024-10-05T01:00:00","datemodified":"2024-10-19T06:33:50","iso3":"CIV","source":"GLOFAS","sourceid":"","polygonlabel":"Centroid","Class":"Point_Centroid","affectedcountries":[{"iso2":"CI","iso3":"CIV","countryname":"Cote d'Ivoire"}],"severitydata":{"severity":0.0,"severitytext":"Magnitude 0 ","severityunit":""}}},{"type":"Feature","bbox":[-8.3415,6.8255,-8.3415,6.8255],"geometry":{"type":"Point","coordinates":[-8.3415,6.8255]},"properties":{"eventtype":"FL","eventid":1102929,"episodeid":1,"eventname":"","glide":"","name":"Flood in Liberia","description":"Flood in Liberia","htmldescription":"Green Flood in Liberia from: 02 Oct 2024 01 to: 04 Oct 2024 01.","icon":"https://www.gdacs.org/images/gdacs_icons/maps/Green/FL.png","iconoverall":"https://www.gdacs.org/images/gdacs_icons/maps/Green/FL.png","url":{"geometry":"https://www.gdacs.org/gdacsapi/api/polygons/getgeometry?eventtype=FL&eventid=1102929&episodeid=1","report":"https://www.gdacs.org/report.aspx?eventid=1102929&episodeid=1&eventtype=FL","details":"https://www.gdacs.org/gdacsapi/api/events/geteventdata?eventtype=FL&eventid=1102929"},"alertlevel":"Green","alertscore":1,"episodealertlevel":"Green","episodealertscore":0.5,"istemporary":"false","iscurrent":"false","country":"Liberia","fromdate":"2024-10-02T01:00:00","todate":"2024-10-04T01:00:00","datemodified":"2024-10-04T10:21:06","iso3":"LBR","source":"GLOFAS","sourceid":"","polygonlabel":"Centroid","Class":"Point_Centroid","affectedcountries":[{"iso2":"LR","iso3":"LBR","countryname":"Liberia"}],"severitydata":{"severity":0.0,"severitytext":"Magnitude 0 ","severityunit":""}}},{"type":"Feature","bbox":[13.909,45.1855,13.909,45.1855],"geometry":{"type":"Point","coordinates":[13.909,45.1855]},"properties":{"eventtype":"FL","eventid":1102930,"episodeid":1,"eventname":"","glide":"","name":"Flood in Croatia, Slovakia","description":"Flood in Croatia, Slovakia","htmldescription":"Green Flood in Croatia, Slovakia from: 02 Oct 2024 01 to: 04 Oct 2024 01.","icon":"https://www.gdacs.org/images/gdacs_icons/maps/Green/FL.png","iconoverall":"https://www.gdacs.org/images/gdacs_icons/maps/Green/FL.png","url":{"geometry":"https://www.gdacs.org/gdacsapi/api/polygons/getgeometry?eventtype=FL&eventid=1102930&episodeid=1","report":"https://www.gdacs.org/report.aspx?eventid=1102930&episodeid=1&eventtype=FL","details":"https://www.gdacs.org/gdacsapi/api/events/geteventdata?eventtype=FL&eventid=1102930"},"alertlevel":"Green","alertscore":1,"episodealertlevel":"Green","episodealertscore":0.5,"istemporary":"false","iscurrent":"false","country":"Croatia, Slovakia","fromdate":"2024-10-02T01:00:00","todate":"2024-10-04T01:00:00","datemodified":"2024-10-04T10:21:28","iso3":"HRV","source":"GLOFAS","sourceid":"","polygonlabel":"Centroid","Class":"Point_Centroid","affectedcountries":[{"iso2":"HR","iso3":"HRV","countryname":"Croatia"},{"iso2":"SK","iso3":"SVK","countryname":"Slovakia"}],"severitydata":{"severity":0.0,"severitytext":"Magnitude 0 ","severityunit":""}}},{"type":"Feature","bbox":[-93.94,17.5635,-93.94,17.5635],"geometry":{"type":"Point","coordinates":[-93.94,17.5635]},"properties":{"eventtype":"FL","eventid":1102885,"episodeid":7,"eventname":"","glide":"","name":"Flood in Mexico","description":"Flood in Mexico","htmldescription":"Green Flood in Mexico from: 30 Aug 2024 01 to: 04 Oct 2024 01.","icon":"https://www.gdacs.org/images/gdacs_icons/maps/Green/FL.png","iconoverall":"https://www.gdacs.org/images/gdacs_icons/maps/Green/FL.png","url":{"geometry":"https://www.gdacs.org/gdacsapi/api/polygons/getgeometry?eventtype=FL&eventid=1102885&episodeid=7","report":"https://www.gdacs.org/report.aspx?eventid=1102885&episodeid=7&eventtype=FL","details":"https://www.gdacs.org/gdacsapi/api/events/geteventdata?eventtype=FL&eventid=1102885"},"alertlevel":"Green","alertscore":1,"episodealertlevel":"Green","episodealertscore":0.5,"istemporary":"false","iscurrent":"false","country":"Mexico","fromdate":"2024-08-30T01:00:00","todate":"2024-10-04T01:00:00","datemodified":"2024-10-04T05:32:11","iso3":"MEX","source":"GLOFAS","sourceid":"","polygonlabel":"Centroid","Class":"Point_Centroid","affectedcountries":[{"iso2":"MX","iso3":"MEX","countryname":"Mexico"}],"severitydata":{"severity":0.0,"severitytext":"Magnitude 0 ","severityunit":""}}},{"type":"Feature","bbox":[57.4903,28.7458,57.4903,28.7458],"geometry":{"type":"Point","coordinates":[57.4903,28.7458]},"properties":{"eventtype":"FL","eventid":1102922,"episodeid":1,"eventname":"","glide":"","name":"Flood in Islamic Republic of Iran","description":"Flood in Islamic Republic of Iran","htmldescription":"Green Flood in Islamic Republic of Iran from: 01 Oct 2024 01 to: 03 Oct 2024 01.","icon":"https://www.gdacs.org/images/gdacs_icons/maps/Green/FL.png","iconoverall":"https://www.gdacs.org/images/gdacs_icons/maps/Green/FL.png","url":{"geometry":"https://www.gdacs.org/gdacsapi/api/polygons/getgeometry?eventtype=FL&eventid=1102922&episodeid=1","report":"https://www.gdacs.org/report.aspx?eventid=1102922&episodeid=1&eventtype=FL","details":"https://www.gdacs.org/gdacsapi/api/events/geteventdata?eventtype=FL&eventid=1102922"},"alertlevel":"Green","alertscore":1,"episodealertlevel":"Green","episodealertscore":0.5,"istemporary":"false","iscurrent":"false","country":"Islamic Republic of Iran","fromdate":"2024-10-01T01:00:00","todate":"2024-10-03T01:00:00","datemodified":"2024-10-03T14:32:08","iso3":"IRN","source":"GLOFAS","sourceid":"","polygonlabel":"Centroid","Class":"Point_Centroid","affectedcountries":[{"iso2":"IR","iso3":"IRN","countryname":"Islamic Republic of Iran"}],"severitydata":{"severity":0.0,"severitytext":"Magnitude 0 ","severityunit":""}}},{"type":"Feature","bbox":[-78.5043,-0.1692,-78.5043,-0.1692],"geometry":{"type":"Point","coordinates":[-78.5043,-0.1692]},"properties":{"eventtype":"FL","eventid":1102927,"episodeid":1,"eventname":"","glide":"","name":"Flood in Ecuador","description":"Flood in Ecuador","htmldescription":"Green Flood in Ecuador from: 01 Oct 2024 01 to: 03 Oct 2024 01.","icon":"https://www.gdacs.org/images/gdacs_icons/maps/Green/FL.png","iconoverall":"https://www.gdacs.org/images/gdacs_icons/maps/Green/FL.png","url":{"geometry":"https://www.gdacs.org/gdacsapi/api/polygons/getgeometry?eventtype=FL&eventid=1102927&episodeid=1","report":"https://www.gdacs.org/report.aspx?eventid=1102927&episodeid=1&eventtype=FL","details":"https://www.gdacs.org/gdacsapi/api/events/geteventdata?eventtype=FL&eventid=1102927"},"alertlevel":"Green","alertscore":1,"episodealertlevel":"Green","episodealertscore":0.5,"istemporary":"false","iscurrent":"false","country":"Ecuador","fromdate":"2024-10-01T01:00:00","todate":"2024-10-03T01:00:00","datemodified":"2024-10-04T05:31:50","iso3":"ECU","source":"GLOFAS","sourceid":"","polygonlabel":"Centroid","Class":"Point_Centroid","affectedcountries":[{"iso2":"EC","iso3":"ECU","countryname":"Ecuador"}],"severitydata":{"severity":0.0,"severitytext":"Magnitude 0 ","severityunit":""}}},{"type":"Feature","bbox":[-13.1757,15.491,-13.1757,15.491],"geometry":{"type":"Point","coordinates":[-13.1757,15.491]},"properties":{"eventtype":"FL","eventid":1102950,"episodeid":1,"eventname":"","glide":"","name":"Flood in Senegal","description":"Flood in Senegal","htmldescription":"Green Flood in Senegal from: 01 Oct 2024 01 to: 03 Oct 2024 01.","icon":"https://www.gdacs.org/images/gdacs_icons/maps/Green/FL.png","iconoverall":"https://www.gdacs.org/images/gdacs_icons/maps/Green/FL.png","url":{"geometry":"https://www.gdacs.org/gdacsapi/api/polygons/getgeometry?eventtype=FL&eventid=1102950&episodeid=1","report":"https://www.gdacs.org/report.aspx?eventid=1102950&episodeid=1&eventtype=FL","details":"https://www.gdacs.org/gdacsapi/api/events/geteventdata?eventtype=FL&eventid=1102950"},"alertlevel":"Green","alertscore":1,"episodealertlevel":"Green","episodealertscore":0.5,"istemporary":"false","iscurrent":"false","country":"Senegal","fromdate":"2024-10-01T01:00:00","todate":"2024-10-03T01:00:00","datemodified":"2024-10-12T07:22:10","iso3":"SEN","source":"GLOFAS","sourceid":"","polygonlabel":"Centroid","Class":"Point_Centroid","affectedcountries":[{"iso2":"SN","iso3":"SEN","countryname":"Senegal"}],"severitydata":{"severity":0.0,"severitytext":"Magnitude 0 ","severityunit":""}}},{"type":"Feature","bbox":[122.7312,12.7503,122.7312,12.7503],"geometry":{"type":"Point","coordinates":[122.7312,12.7503]},"properties":{"eventtype":"FL","eventid":1102924,"episodeid":1,"eventname":"","glide":"","name":"Flood in Philippines","description":"Flood in Philippines","htmldescription":"Green Flood in Philippines from: 30 Sep 2024 01 to: 02 Oct 2024 01.","icon":"https://www.gdacs.org/images/gdacs_icons/maps/Green/FL.png","iconoverall":"https://www.gdacs.org/images/gdacs_icons/maps/Green/FL.png","url":{"geometry":"https://www.gdacs.org/gdacsapi/api/polygons/getgeometry?eventtype=FL&eventid=1102924&episodeid=1","report":"https://www.gdacs.org/report.aspx?eventid=1102924&episodeid=1&eventtype=FL","details":"https://www.gdacs.org/gdacsapi/api/events/geteventdata?eventtype=FL&eventid=1102924"},"alertlevel":"Green","alertscore":1,"episodealertlevel":"Green","episodealertscore":0.5,"istemporary":"false","iscurrent":"false","country":"Philippines","fromdate":"2024-09-30T01:00:00","todate":"2024-10-02T01:00:00","datemodified":"2024-10-03T14:33:09","iso3":"PHL","source":"GLOFAS","sourceid":"","polygonlabel":"Centroid","Class":"Point_Centroid","affectedcountries":[{"iso2":"PH","iso3":"PHL","countryname":"Philippines"}],"severitydata":{"severity":0.0,"severitytext":"Magnitude 0 ","severityunit":""}}},{"type":"Feature","bbox":[-82.0303,8.55,-82.0303,8.55],"geometry":{"type":"Point","coordinates":[-82.0303,8.55]},"properties":{"eventtype":"FL","eventid":1102919,"episodeid":1,"eventname":"","glide":"","name":"Flood in Panama","description":"Flood in Panama","htmldescription":"Green Flood in Panama from: 29 Sep 2024 01 to: 01 Oct 2024 01.","icon":"https://www.gdacs.org/images/gdacs_icons/maps/Green/FL.png","iconoverall":"https://www.gdacs.org/images/gdacs_icons/maps/Green/FL.png","url":{"geometry":"https://www.gdacs.org/gdacsapi/api/polygons/getgeometry?eventtype=FL&eventid=1102919&episodeid=1","report":"https://www.gdacs.org/report.aspx?eventid=1102919&episodeid=1&eventtype=FL","details":"https://www.gdacs.org/gdacsapi/api/events/geteventdata?eventtype=FL&eventid=1102919"},"alertlevel":"Green","alertscore":1,"episodealertlevel":"Green","episodealertscore":0.5,"istemporary":"false","iscurrent":"false","country":"Panama","fromdate":"2024-09-29T01:00:00","todate":"2024-10-01T01:00:00","datemodified":"2024-10-03T05:31:27","iso3":"PAN","source":"GLOFAS","sourceid":"","polygonlabel":"Centroid","Class":"Point_Centroid","affectedcountries":[{"iso2":"PA","iso3":"PAN","countryname":"Panama"}],"severitydata":{"severity":0.0,"severitytext":"Magnitude 0 ","severityunit":""}}}],"bbox":null}