{"type":"FeatureCollection","features":[{"type":"Feature","bbox":[37.169,-17.236,37.169,-17.236],"geometry":{"type":"Point","coordinates":[37.169,-17.236]},"properties":{"eventtype":"FL","eventid":2773,"episodeid":1,"eventname":null,"glide":"","name":"Flood in Malawi","description":"Flood in Malawi","htmldescription":"GREEN Flood in Malawi from: 22 Dec 2005 00 to: 07 Feb 2006 23.","icon":"https://www.gdacs.org/images/gdacs_icons/maps/GREEN/FL.png","iconoverall":"https://www.gdacs.org/images/gdacs_icons/maps/GREEN/FL.png","url":{"geometry":"https://www.gdacs.org/gdacsapi/api/polygons/getgeometry?eventtype=FL&eventid=2773&episodeid=1","report":"https://www.gdacs.org/report.aspx?eventid=2773&episodeid=1&eventtype=FL","details":"https://www.gdacs.org/gdacsapi/api/events/geteventdata?eventtype=FL&eventid=2773"},"alertlevel":"GREEN","alertscore":1,"episodealertlevel":"GREEN","episodealertscore":1.0,"istemporary":"false","iscurrent":"false","country":"Malawi","fromdate":"2005-12-22T00:00:00","todate":"2006-02-07T23:59:59","datemodified":"2025-01-30T12:25:32.333","iso3":"MWI","source":"DFO","sourceid":"","polygonlabel":"Centroid","Class":"Point_Centroid","affectedcountries":[{"iso2":"MW","iso3":"MWI","countryname":"Malawi"}],"severitydata":{"severity":7.33,"severitytext":"Magnitude 7.33","severityunit":""}}},{"type":"Feature","bbox":[11.93,64.15,11.93,64.15],"geometry":{"type":"Point","coordinates":[11.93,64.15]},"properties":{"eventtype":"FL","eventid":2790,"episodeid":1,"eventname":"","glide":"","name":"Flood in Norway","description":"Flood in Norway","htmldescription":"GREEN Flood in Norway from: 30 Jan 2006 00 to: 30 Jan 2006 00.","icon":"https://www.gdacs.org/images/gdacs_icons/maps/Green/FL.png","iconoverall":"https://www.gdacs.org/images/gdacs_icons/maps/GREEN/FL.png","url":{"geometry":"https://www.gdacs.org/gdacsapi/api/polygons/getgeometry?eventtype=FL&eventid=2790&episodeid=1","report":"https://www.gdacs.org/report.aspx?eventid=2790&episodeid=1&eventtype=FL","details":"https://www.gdacs.org/gdacsapi/api/events/geteventdata?eventtype=FL&eventid=2790"},"alertlevel":"GREEN","alertscore":1,"episodealertlevel":"Green","episodealertscore":1.0,"istemporary":"false","iscurrent":"false","country":"Norway","fromdate":"2006-01-30T00:00:00","todate":"2006-01-30T00:00:00","datemodified":"2006-01-30T00:00:00","iso3":"   ","source":"DFO","sourceid":"","polygonlabel":"Centroid","Class":"Point_Centroid","affectedcountries":[{"iso2":"NO","iso3":"NOR","countryname":"Norway"}],"severitydata":{"severity":5.7,"severitytext":"Magnitude 5.70","severityunit":""}}},{"type":"Feature","bbox":[177.68,-17.82,177.68,-17.82],"geometry":{"type":"Point","coordinates":[177.68,-17.82]},"properties":{"eventtype":"FL","eventid":2791,"episodeid":1,"eventname":"","glide":"","name":"Flood in Fiji","description":"Flood in Fiji","htmldescription":"GREEN Flood in Fiji from: 29 Jan 2006 00 to: 29 Jan 2006 00.","icon":"https://www.gdacs.org/images/gdacs_icons/maps/Green/FL.png","iconoverall":"https://www.gdacs.org/images/gdacs_icons/maps/GREEN/FL.png","url":{"geometry":"https://www.gdacs.org/gdacsapi/api/polygons/getgeometry?eventtype=FL&eventid=2791&episodeid=1","report":"https://www.gdacs.org/report.aspx?eventid=2791&episodeid=1&eventtype=FL","details":"https://www.gdacs.org/gdacsapi/api/events/geteventdata?eventtype=FL&eventid=2791"},"alertlevel":"GREEN","alertscore":1,"episodealertlevel":"Green","episodealertscore":1.0,"istemporary":"false","iscurrent":"false","country":"Fiji","fromdate":"2006-01-29T00:00:00","todate":"2006-01-29T00:00:00","datemodified":"2006-01-29T00:00:00","iso3":"   ","source":"DFO","sourceid":"","polygonlabel":"Centroid","Class":"Point_Centroid","affectedcountries":[{"iso2":"FJ","iso3":"FJI","countryname":"Fiji"}],"severitydata":{"severity":4.75,"severitytext":"Magnitude 4.75","severityunit":""}}},{"type":"Feature","bbox":[-43.36,-22.56,-43.36,-22.56],"geometry":{"type":"Point","coordinates":[-43.36,-22.56]},"properties":{"eventtype":"FL","eventid":2787,"episodeid":1,"eventname":"","glide":"FL-2006-000017-BRA","name":"Flood in Brazil","description":"Flood in Brazil","htmldescription":"GREEN Flood in Brazil from: 27 Jan 2006 00 to: 27 Jan 2006 00.","icon":"https://www.gdacs.org/images/gdacs_icons/maps/Green/FL.png","iconoverall":"https://www.gdacs.org/images/gdacs_icons/maps/GREEN/FL.png","url":{"geometry":"https://www.gdacs.org/gdacsapi/api/polygons/getgeometry?eventtype=FL&eventid=2787&episodeid=1","report":"https://www.gdacs.org/report.aspx?eventid=2787&episodeid=1&eventtype=FL","details":"https://www.gdacs.org/gdacsapi/api/events/geteventdata?eventtype=FL&eventid=2787"},"alertlevel":"GREEN","alertscore":1,"episodealertlevel":"Green","episodealertscore":1.0,"istemporary":"false","iscurrent":"false","country":"Brazil","fromdate":"2006-01-27T00:00:00","todate":"2006-01-27T00:00:00","datemodified":"2006-01-27T00:00:00","iso3":"   ","source":"DFO","sourceid":"","polygonlabel":"Centroid","Class":"Point_Centroid","affectedcountries":[{"iso2":"BR","iso3":"BRA","countryname":"Brazil"}],"severitydata":{"severity":4.57,"severitytext":"Magnitude 4.57","severityunit":""}}},{"type":"Feature","bbox":[121.82,17.02,121.82,17.02],"geometry":{"type":"Point","coordinates":[121.82,17.02]},"properties":{"eventtype":"FL","eventid":2785,"episodeid":1,"eventname":"","glide":"","name":"Flood in Philippines","description":"Flood in Philippines","htmldescription":"ORANGE Flood in Philippines from: 26 Jan 2006 00 to: 26 Jan 2006 00.","icon":"https://www.gdacs.org/images/gdacs_icons/maps/Orange/FL.png","iconoverall":"https://www.gdacs.org/images/gdacs_icons/maps/ORANGE/FL.png","url":{"geometry":"https://www.gdacs.org/gdacsapi/api/polygons/getgeometry?eventtype=FL&eventid=2785&episodeid=1","report":"https://www.gdacs.org/report.aspx?eventid=2785&episodeid=1&eventtype=FL","details":"https://www.gdacs.org/gdacsapi/api/events/geteventdata?eventtype=FL&eventid=2785"},"alertlevel":"ORANGE","alertscore":2,"episodealertlevel":"Orange","episodealertscore":2.0,"istemporary":"false","iscurrent":"false","country":"Philippines","fromdate":"2006-01-26T00:00:00","todate":"2006-01-26T00:00:00","datemodified":"2006-01-26T00:00:00","iso3":"   ","source":"DFO","sourceid":"","polygonlabel":"Centroid","Class":"Point_Centroid","affectedcountries":[{"iso2":"PH","iso3":"PHL","countryname":"Philippines"}],"severitydata":{"severity":5.84,"severitytext":"Magnitude 5.84","severityunit":""}}},{"type":"Feature","bbox":[108.59,-6.85,108.59,-6.85],"geometry":{"type":"Point","coordinates":[108.59,-6.85]},"properties":{"eventtype":"FL","eventid":2789,"episodeid":1,"eventname":"","glide":"","name":"Flood in Indonesia","description":"Flood in Indonesia","htmldescription":"GREEN Flood in Indonesia from: 26 Jan 2006 00 to: 26 Jan 2006 00.","icon":"https://www.gdacs.org/images/gdacs_icons/maps/Green/FL.png","iconoverall":"https://www.gdacs.org/images/gdacs_icons/maps/GREEN/FL.png","url":{"geometry":"https://www.gdacs.org/gdacsapi/api/polygons/getgeometry?eventtype=FL&eventid=2789&episodeid=1","report":"https://www.gdacs.org/report.aspx?eventid=2789&episodeid=1&eventtype=FL","details":"https://www.gdacs.org/gdacsapi/api/events/geteventdata?eventtype=FL&eventid=2789"},"alertlevel":"GREEN","alertscore":1,"episodealertlevel":"Green","episodealertscore":1.0,"istemporary":"false","iscurrent":"false","country":"Indonesia","fromdate":"2006-01-26T00:00:00","todate":"2006-01-26T00:00:00","datemodified":"2006-01-26T00:00:00","iso3":"   ","source":"DFO","sourceid":"","polygonlabel":"Centroid","Class":"Point_Centroid","affectedcountries":[{"iso2":"ID","iso3":"IDN","countryname":"Indonesia"}],"severitydata":{"severity":6.16,"severitytext":"Magnitude 6.16","severityunit":""}}},{"type":"Feature","bbox":[-63.43,-16.03,-63.43,-16.03],"geometry":{"type":"Point","coordinates":[-63.43,-16.03]},"properties":{"eventtype":"FL","eventid":2786,"episodeid":1,"eventname":"","glide":"FL-2006-000010-BOL","name":"Flood in Bolivia","description":"Flood in Bolivia","htmldescription":"ORANGE Flood in Bolivia from: 25 Jan 2006 00 to: 25 Jan 2006 00.","icon":"https://www.gdacs.org/images/gdacs_icons/maps/Orange/FL.png","iconoverall":"https://www.gdacs.org/images/gdacs_icons/maps/ORANGE/FL.png","url":{"geometry":"https://www.gdacs.org/gdacsapi/api/polygons/getgeometry?eventtype=FL&eventid=2786&episodeid=1","report":"https://www.gdacs.org/report.aspx?eventid=2786&episodeid=1&eventtype=FL","details":"https://www.gdacs.org/gdacsapi/api/events/geteventdata?eventtype=FL&eventid=2786"},"alertlevel":"ORANGE","alertscore":2,"episodealertlevel":"Orange","episodealertscore":2.0,"istemporary":"false","iscurrent":"false","country":"Bolivia","fromdate":"2006-01-25T00:00:00","todate":"2006-01-25T00:00:00","datemodified":"2006-01-25T00:00:00","iso3":"   ","source":"DFO","sourceid":"","polygonlabel":"Centroid","Class":"Point_Centroid","affectedcountries":[{"iso2":"BO","iso3":"BOL","countryname":"Bolivia"}],"severitydata":{"severity":7.9,"severitytext":"Magnitude 7.90","severityunit":""}}},{"type":"Feature","bbox":[117.29,-8.44,117.29,-8.44],"geometry":{"type":"Point","coordinates":[117.29,-8.44]},"properties":{"eventtype":"FL","eventid":2788,"episodeid":1,"eventname":"","glide":"","name":"Flood in Indonesia","description":"Flood in Indonesia","htmldescription":"GREEN Flood in Indonesia from: 22 Jan 2006 00 to: 22 Jan 2006 00.","icon":"https://www.gdacs.org/images/gdacs_icons/maps/Green/FL.png","iconoverall":"https://www.gdacs.org/images/gdacs_icons/maps/GREEN/FL.png","url":{"geometry":"https://www.gdacs.org/gdacsapi/api/polygons/getgeometry?eventtype=FL&eventid=2788&episodeid=1","report":"https://www.gdacs.org/report.aspx?eventid=2788&episodeid=1&eventtype=FL","details":"https://www.gdacs.org/gdacsapi/api/events/geteventdata?eventtype=FL&eventid=2788"},"alertlevel":"GREEN","alertscore":1,"episodealertlevel":"Green","episodealertscore":1.0,"istemporary":"false","iscurrent":"false","country":"Indonesia","fromdate":"2006-01-22T00:00:00","todate":"2006-01-22T00:00:00","datemodified":"2006-01-22T00:00:00","iso3":"   ","source":"DFO","sourceid":"","polygonlabel":"Centroid","Class":"Point_Centroid","affectedcountries":[{"iso2":"ID","iso3":"IDN","countryname":"Indonesia"}],"severitydata":{"severity":5.46,"severitytext":"Magnitude 5.46","severityunit":""}}},{"type":"Feature","bbox":[15.71,-25.48,15.71,-25.48],"geometry":{"type":"Point","coordinates":[15.71,-25.48]},"properties":{"eventtype":"FL","eventid":2783,"episodeid":1,"eventname":"","glide":"","name":"Flood in Namibia","description":"Flood in Namibia","htmldescription":"GREEN Flood in Namibia from: 18 Jan 2006 00 to: 18 Jan 2006 00.","icon":"https://www.gdacs.org/images/gdacs_icons/maps/Green/FL.png","iconoverall":"https://www.gdacs.org/images/gdacs_icons/maps/GREEN/FL.png","url":{"geometry":"https://www.gdacs.org/gdacsapi/api/polygons/getgeometry?eventtype=FL&eventid=2783&episodeid=1","report":"https://www.gdacs.org/report.aspx?eventid=2783&episodeid=1&eventtype=FL","details":"https://www.gdacs.org/gdacsapi/api/events/geteventdata?eventtype=FL&eventid=2783"},"alertlevel":"GREEN","alertscore":1,"episodealertlevel":"Green","episodealertscore":1.0,"istemporary":"false","iscurrent":"false","country":"Namibia","fromdate":"2006-01-18T00:00:00","todate":"2006-01-18T00:00:00","datemodified":"2006-01-18T00:00:00","iso3":"   ","source":"DFO","sourceid":"","polygonlabel":"Centroid","Class":"Point_Centroid","affectedcountries":[{"iso2":"NA","iso3":"NAM","countryname":"Namibia"}],"severitydata":{"severity":3.11,"severitytext":"Magnitude 3.11","severityunit":""}}},{"type":"Feature","bbox":[-61.24,10.32,-61.24,10.32],"geometry":{"type":"Point","coordinates":[-61.24,10.32]},"properties":{"eventtype":"FL","eventid":2781,"episodeid":1,"eventname":"","glide":"","name":"Flood in Trinidad","description":"Flood in Trinidad","htmldescription":"GREEN Flood in Trinidad from: 14 Jan 2006 00 to: 14 Jan 2006 00.","icon":"https://www.gdacs.org/images/gdacs_icons/maps/Green/FL.png","iconoverall":"https://www.gdacs.org/images/gdacs_icons/maps/GREEN/FL.png","url":{"geometry":"https://www.gdacs.org/gdacsapi/api/polygons/getgeometry?eventtype=FL&eventid=2781&episodeid=1","report":"https://www.gdacs.org/report.aspx?eventid=2781&episodeid=1&eventtype=FL","details":"https://www.gdacs.org/gdacsapi/api/events/geteventdata?eventtype=FL&eventid=2781"},"alertlevel":"GREEN","alertscore":1,"episodealertlevel":"Green","episodealertscore":1.0,"istemporary":"false","iscurrent":"false","country":"Trinidad","fromdate":"2006-01-14T00:00:00","todate":"2006-01-14T00:00:00","datemodified":"2006-01-14T00:00:00","iso3":"   ","source":"DFO","sourceid":"","polygonlabel":"Centroid","Class":"Point_Centroid","affectedcountries":[],"severitydata":{"severity":4.26,"severitytext":"Magnitude 4.26","severityunit":""}}},{"type":"Feature","bbox":[100.124,7.205,100.124,7.205],"geometry":{"type":"Point","coordinates":[100.124,7.205]},"properties":{"eventtype":"FL","eventid":2768,"episodeid":1,"eventname":null,"glide":"","name":"Flood in Thailand","description":"Flood in Thailand","htmldescription":"ORANGE Flood in Thailand from: 23 Nov 2005 00 to: 12 Jan 2006 23.","icon":"https://www.gdacs.org/images/gdacs_icons/maps/ORANGE/FL.png","iconoverall":"https://www.gdacs.org/images/gdacs_icons/maps/ORANGE/FL.png","url":{"geometry":"https://www.gdacs.org/gdacsapi/api/polygons/getgeometry?eventtype=FL&eventid=2768&episodeid=1","report":"https://www.gdacs.org/report.aspx?eventid=2768&episodeid=1&eventtype=FL","details":"https://www.gdacs.org/gdacsapi/api/events/geteventdata?eventtype=FL&eventid=2768"},"alertlevel":"ORANGE","alertscore":2,"episodealertlevel":"ORANGE","episodealertscore":2.0,"istemporary":"false","iscurrent":"false","country":"Thailand","fromdate":"2005-11-23T00:00:00","todate":"2006-01-12T23:59:59","datemodified":"2025-01-30T12:25:32.793","iso3":"THA","source":"DFO","sourceid":"","polygonlabel":"Centroid","Class":"Point_Centroid","affectedcountries":[{"iso2":"TH","iso3":"THA","countryname":"Thailand"}],"severitydata":{"severity":6.86,"severitytext":"Magnitude 6.86","severityunit":""}}},{"type":"Feature","bbox":[116.94,-23.26,116.94,-23.26],"geometry":{"type":"Point","coordinates":[116.94,-23.26]},"properties":{"eventtype":"FL","eventid":2780,"episodeid":1,"eventname":"","glide":"","name":"Flood in Australia","description":"Flood in Australia","htmldescription":"GREEN Flood in Australia from: 09 Jan 2006 00 to: 09 Jan 2006 00.","icon":"https://www.gdacs.org/images/gdacs_icons/maps/Green/FL.png","iconoverall":"https://www.gdacs.org/images/gdacs_icons/maps/GREEN/FL.png","url":{"geometry":"https://www.gdacs.org/gdacsapi/api/polygons/getgeometry?eventtype=FL&eventid=2780&episodeid=1","report":"https://www.gdacs.org/report.aspx?eventid=2780&episodeid=1&eventtype=FL","details":"https://www.gdacs.org/gdacsapi/api/events/geteventdata?eventtype=FL&eventid=2780"},"alertlevel":"GREEN","alertscore":1,"episodealertlevel":"Green","episodealertscore":1.0,"istemporary":"false","iscurrent":"false","country":"Australia","fromdate":"2006-01-09T00:00:00","todate":"2006-01-09T00:00:00","datemodified":"2006-01-09T00:00:00","iso3":"   ","source":"DFO","sourceid":"","polygonlabel":"Centroid","Class":"Point_Centroid","affectedcountries":[{"iso2":"AU","iso3":"AUS","countryname":"Australia"}],"severitydata":{"severity":7.57,"severitytext":"Magnitude 7.57","severityunit":""}}},{"type":"Feature","bbox":[108.215,-6.382,108.215,-6.382],"geometry":{"type":"Point","coordinates":[108.215,-6.382]},"properties":{"eventtype":"FL","eventid":2779,"episodeid":1,"eventname":"","glide":"","name":"Flood in Indonesia","description":"Flood in Indonesia","htmldescription":"GREEN Flood in Indonesia from: 08 Jan 2006 00 to: 08 Jan 2006 00.","icon":"https://www.gdacs.org/images/gdacs_icons/maps/Green/FL.png","iconoverall":"https://www.gdacs.org/images/gdacs_icons/maps/GREEN/FL.png","url":{"geometry":"https://www.gdacs.org/gdacsapi/api/polygons/getgeometry?eventtype=FL&eventid=2779&episodeid=1","report":"https://www.gdacs.org/report.aspx?eventid=2779&episodeid=1&eventtype=FL","details":"https://www.gdacs.org/gdacsapi/api/events/geteventdata?eventtype=FL&eventid=2779"},"alertlevel":"GREEN","alertscore":1,"episodealertlevel":"Green","episodealertscore":1.0,"istemporary":"false","iscurrent":"false","country":"Indonesia","fromdate":"2006-01-08T00:00:00","todate":"2006-01-08T00:00:00","datemodified":"2006-01-08T00:00:00","iso3":"   ","source":"DFO","sourceid":"","polygonlabel":"Centroid","Class":"Point_Centroid","affectedcountries":[{"iso2":"ID","iso3":"IDN","countryname":"Indonesia"}],"severitydata":{"severity":3.66,"severitytext":"Magnitude 3.66","severityunit":""}}},{"type":"Feature","bbox":[-58.66,6.89,-58.66,6.89],"geometry":{"type":"Point","coordinates":[-58.66,6.89]},"properties":{"eventtype":"FL","eventid":2782,"episodeid":1,"eventname":"","glide":"FL-2006-000009-GUY","name":"Flood in Guyana","description":"Flood in Guyana","htmldescription":"GREEN Flood in Guyana from: 08 Jan 2006 00 to: 08 Jan 2006 00.","icon":"https://www.gdacs.org/images/gdacs_icons/maps/Green/FL.png","iconoverall":"https://www.gdacs.org/images/gdacs_icons/maps/GREEN/FL.png","url":{"geometry":"https://www.gdacs.org/gdacsapi/api/polygons/getgeometry?eventtype=FL&eventid=2782&episodeid=1","report":"https://www.gdacs.org/report.aspx?eventid=2782&episodeid=1&eventtype=FL","details":"https://www.gdacs.org/gdacsapi/api/events/geteventdata?eventtype=FL&eventid=2782"},"alertlevel":"GREEN","alertscore":1,"episodealertlevel":"Green","episodealertscore":1.0,"istemporary":"false","iscurrent":"false","country":"Guyana","fromdate":"2006-01-08T00:00:00","todate":"2006-01-08T00:00:00","datemodified":"2006-01-08T00:00:00","iso3":"   ","source":"DFO","sourceid":"","polygonlabel":"Centroid","Class":"Point_Centroid","affectedcountries":[{"iso2":"GY","iso3":"GUY","countryname":"Guyana"}],"severitydata":{"severity":5.96,"severitytext":"Magnitude 5.96","severityunit":""}}},{"type":"Feature","bbox":[19.583,47.717,19.583,47.717],"geometry":{"type":"Point","coordinates":[19.583,47.717]},"properties":{"eventtype":"FL","eventid":2778,"episodeid":1,"eventname":"","glide":"","name":"Flood in Hungary","description":"Flood in Hungary","htmldescription":"GREEN Flood in Hungary from: 03 Jan 2006 00 to: 03 Jan 2006 00.","icon":"https://www.gdacs.org/images/gdacs_icons/maps/Green/FL.png","iconoverall":"https://www.gdacs.org/images/gdacs_icons/maps/GREEN/FL.png","url":{"geometry":"https://www.gdacs.org/gdacsapi/api/polygons/getgeometry?eventtype=FL&eventid=2778&episodeid=1","report":"https://www.gdacs.org/report.aspx?eventid=2778&episodeid=1&eventtype=FL","details":"https://www.gdacs.org/gdacsapi/api/events/geteventdata?eventtype=FL&eventid=2778"},"alertlevel":"GREEN","alertscore":1,"episodealertlevel":"Green","episodealertscore":1.0,"istemporary":"false","iscurrent":"false","country":"Hungary","fromdate":"2006-01-03T00:00:00","todate":"2006-01-03T00:00:00","datemodified":"2006-01-03T00:00:00","iso3":"   ","source":"DFO","sourceid":"","polygonlabel":"Centroid","Class":"Point_Centroid","affectedcountries":[{"iso2":"HU","iso3":"HUN","countryname":"Hungary"}],"severitydata":{"severity":5.62,"severitytext":"Magnitude 5.62","severityunit":""}}},{"type":"Feature","bbox":[26.47,41.55,26.47,41.55],"geometry":{"type":"Point","coordinates":[26.47,41.55]},"properties":{"eventtype":"FL","eventid":2784,"episodeid":1,"eventname":"","glide":"","name":"Flood in Greece","description":"Flood in Greece","htmldescription":"GREEN Flood in Greece from: 02 Jan 2006 00 to: 02 Jan 2006 00.","icon":"https://www.gdacs.org/images/gdacs_icons/maps/Green/FL.png","iconoverall":"https://www.gdacs.org/images/gdacs_icons/maps/GREEN/FL.png","url":{"geometry":"https://www.gdacs.org/gdacsapi/api/polygons/getgeometry?eventtype=FL&eventid=2784&episodeid=1","report":"https://www.gdacs.org/report.aspx?eventid=2784&episodeid=1&eventtype=FL","details":"https://www.gdacs.org/gdacsapi/api/events/geteventdata?eventtype=FL&eventid=2784"},"alertlevel":"GREEN","alertscore":1,"episodealertlevel":"Green","episodealertscore":1.0,"istemporary":"false","iscurrent":"false","country":"Greece","fromdate":"2006-01-02T00:00:00","todate":"2006-01-02T00:00:00","datemodified":"2006-01-02T00:00:00","iso3":"   ","source":"DFO","sourceid":"","polygonlabel":"Centroid","Class":"Point_Centroid","affectedcountries":[{"iso2":"GR","iso3":"GRC","countryname":"Greece"}],"severitydata":{"severity":4.94,"severitytext":"Magnitude 4.94","severityunit":""}}},{"type":"Feature","bbox":[113.342,-8.023,113.342,-8.023],"geometry":{"type":"Point","coordinates":[113.342,-8.023]},"properties":{"eventtype":"FL","eventid":2777,"episodeid":1,"eventname":"","glide":"FL-2006-000001-IDN","name":"Flood in Indonesia","description":"Flood in Indonesia","htmldescription":"ORANGE Flood in Indonesia from: 01 Jan 2006 00 to: 01 Jan 2006 00.","icon":"https://www.gdacs.org/images/gdacs_icons/maps/Orange/FL.png","iconoverall":"https://www.gdacs.org/images/gdacs_icons/maps/ORANGE/FL.png","url":{"geometry":"https://www.gdacs.org/gdacsapi/api/polygons/getgeometry?eventtype=FL&eventid=2777&episodeid=1","report":"https://www.gdacs.org/report.aspx?eventid=2777&episodeid=1&eventtype=FL","details":"https://www.gdacs.org/gdacsapi/api/events/geteventdata?eventtype=FL&eventid=2777"},"alertlevel":"ORANGE","alertscore":2,"episodealertlevel":"Orange","episodealertscore":2.0,"istemporary":"false","iscurrent":"false","country":"Indonesia","fromdate":"2006-01-01T00:00:00","todate":"2006-01-01T00:00:00","datemodified":"2006-01-01T00:00:00","iso3":"   ","source":"DFO","sourceid":"","polygonlabel":"Centroid","Class":"Point_Centroid","affectedcountries":[{"iso2":"ID","iso3":"IDN","countryname":"Indonesia"}],"severitydata":{"severity":4.01,"severitytext":"Magnitude 4.01","severityunit":""}}}],"bbox":null}